[{"mainVersionId":"SFN20211464","title":"Anyone But You","genres":[],"lengthInMinutes":103,"rating":"12 \u00e5r","poster":{"versions":[{"url":"https:\/\/www.filmweb.no\/article1518767.ece\/REPRESENTATIONS\/poster_100x141\/Anyone%20But%20You%20A4%20skjerm%20-%20Teaser"},{"url":"https:\/\/www.filmweb.no\/article1518767.ece\/REPRESENTATIONS\/poster_200x282\/Anyone%20But%20You%20A4%20skjerm%20-%20Teaser"},{"url":"https:\/\/www.filmweb.no\/article1518767.ece\/REPRESENTATIONS\/poster_300x424\/Anyone%20But%20You%20A4%20skjerm%20-%20Teaser"},{"url":"https:\/\/www.filmweb.no\/article1518767.ece\/REPRESENTATIONS\/poster_400x564\/Anyone%20But%20You%20A4%20skjerm%20-%20Teaser"},{"url":"https:\/\/www.filmweb.no\/article1518767.ece\/REPRESENTATIONS\/poster_600x848\/Anyone%20But%20You%20A4%20skjerm%20-%20Teaser"}]},"sanityImagePosterUrl":"https:\/\/cdn.sanity.io\/images\/j0wdmpyb\/production\/4ca32bf8c509d0c9d25a3162e0a646ee0865921d-1240x1754.jpg?auto=format","shows":[{"firmName":"KinoCity","showStart":"2024-02-08T20:30:00","screenName":"Sal 4 - Perfekt","ticketSaleUrl":"https:\/\/www.nfkino.no\/showtime\/1021\/74839\/","theaterName":"KinoCity","movieVersionId":"SFN20211464"},{"firmName":"KinoCity","showStart":"2024-02-09T18:00:00","screenName":"Sal 4 - Perfekt","ticketSaleUrl":"https:\/\/www.nfkino.no\/showtime\/1021\/74892\/","theaterName":"KinoCity","movieVersionId":"SFN20211464"},{"firmName":"KinoCity","showStart":"2024-02-10T18:00:00","screenName":"Sal 4 - Perfekt","ticketSaleUrl":"https:\/\/www.nfkino.no\/showtime\/1021\/74917\/","theaterName":"KinoCity","movieVersionId":"SFN20211464"},{"firmName":"KinoCity","showStart":"2024-02-11T18:00:00","screenName":"Sal 4 - Perfekt","ticketSaleUrl":"https:\/\/www.nfkino.no\/showtime\/1021\/74950\/","theaterName":"KinoCity","movieVersionId":"SFN20211464"},{"firmName":"KinoCity","showStart":"2024-02-12T18:00:00","screenName":"Sal 4 - Perfekt","ticketSaleUrl":"https:\/\/www.nfkino.no\/showtime\/1021\/74973\/","theaterName":"KinoCity","movieVersionId":"SFN20211464"},{"firmName":"KinoCity","showStart":"2024-02-13T18:00:00","screenName":"Sal 4 - Perfekt","ticketSaleUrl":"https:\/\/www.nfkino.no\/showtime\/1021\/74996\/","theaterName":"KinoCity","movieVersionId":"SFN20211464"},{"firmName":"KinoCity","showStart":"2024-02-14T14:30:00","screenName":"Sal 4 - Perfekt","ticketSaleUrl":"https:\/\/www.nfkino.no\/showtime\/1021\/75022\/","theaterName":"KinoCity","movieVersionId":"SFN20211464"},{"firmName":"KinoCity","showStart":"2024-02-15T14:30:00","screenName":"Sal 4 - Perfekt","ticketSaleUrl":"https:\/\/www.nfkino.no\/showtime\/1021\/75037\/","theaterName":"KinoCity","movieVersionId":"SFN20211464"}]},{"mainVersionId":"UIP20231595","title":"Argylle","genres":["Action","Thriller"],"lengthInMinutes":139,"rating":"12 \u00e5r","poster":{"versions":[{"url":"https:\/\/www.filmweb.no\/article1517690.ece\/REPRESENTATIONS\/poster_100x141\/Argylle%20Midlertidig%20thumbnail%20for%20Filmweb"},{"url":"https:\/\/www.filmweb.no\/article1517690.ece\/REPRESENTATIONS\/poster_200x282\/Argylle%20Midlertidig%20thumbnail%20for%20Filmweb"},{"url":"https:\/\/www.filmweb.no\/article1517690.ece\/REPRESENTATIONS\/poster_300x424\/Argylle%20Midlertidig%20thumbnail%20for%20Filmweb"},{"url":"https:\/\/www.filmweb.no\/article1517690.ece\/REPRESENTATIONS\/poster_400x564\/Argylle%20Midlertidig%20thumbnail%20for%20Filmweb"},{"url":"https:\/\/www.filmweb.no\/article1517690.ece\/REPRESENTATIONS\/poster_600x848\/Argylle%20Midlertidig%20thumbnail%20for%20Filmweb"}]},"sanityImagePosterUrl":"https:\/\/cdn.sanity.io\/images\/j0wdmpyb\/production\/d2e337648b29e34d5bdce432b988a0a8c9950a1b-1500x2122.webp?auto=format","shows":[{"firmName":"KinoCity","showStart":"2024-02-08T21:10:00","screenName":"Sal 1 - Saga","ticketSaleUrl":"https:\/\/www.nfkino.no\/showtime\/1021\/74828\/","theaterName":"KinoCity","movieVersionId":"UIP20231595"},{"firmName":"KinoCity","showStart":"2024-02-09T21:15:00","screenName":"Sal 3 - Palads","ticketSaleUrl":"https:\/\/www.nfkino.no\/showtime\/1021\/74882\/","theaterName":"KinoCity","movieVersionId":"UIP20231595"},{"firmName":"KinoCity","showStart":"2024-02-10T21:15:00","screenName":"Sal 3 - Palads","ticketSaleUrl":"https:\/\/www.nfkino.no\/showtime\/1021\/74913\/","theaterName":"KinoCity","movieVersionId":"UIP20231595"},{"firmName":"KinoCity","showStart":"2024-02-11T21:15:00","screenName":"Sal 3 - Palads","ticketSaleUrl":"https:\/\/www.nfkino.no\/showtime\/1021\/74946\/","theaterName":"KinoCity","movieVersionId":"UIP20231595"},{"firmName":"KinoCity","showStart":"2024-02-12T21:15:00","screenName":"Sal 3 - Palads","ticketSaleUrl":"https:\/\/www.nfkino.no\/showtime\/1021\/74970\/","theaterName":"KinoCity","movieVersionId":"UIP20231595"},{"firmName":"KinoCity","showStart":"2024-02-13T21:15:00","screenName":"Sal 3 - Palads","ticketSaleUrl":"https:\/\/www.nfkino.no\/showtime\/1021\/74993\/","theaterName":"KinoCity","movieVersionId":"UIP20231595"},{"firmName":"KinoCity","showStart":"2024-02-14T21:15:00","screenName":"Sal 3 - Palads","ticketSaleUrl":"https:\/\/www.nfkino.no\/showtime\/1021\/75009\/","theaterName":"KinoCity","movieVersionId":"UIP20231595"},{"firmName":"KinoCity","showStart":"2024-02-15T21:15:00","screenName":"Sal 3 - Palads","ticketSaleUrl":"https:\/\/www.nfkino.no\/showtime\/1021\/75036\/","theaterName":"KinoCity","movieVersionId":"UIP20231595"}]},{"mainVersionId":"MPL20240051","title":"BABY BOOM CZYLI KOGEL MOGEL 5","genres":[],"lengthInMinutes":0,"rating":"","poster":null,"sanityImagePosterUrl":"https:\/\/cdn.sanity.io\/images\/j0wdmpyb\/production\/c4126a45726c3453a70cca2bdf0f0b553c3cde02-1060x1484.jpg?auto=format","shows":[{"firmName":"KinoCity","showStart":"2024-02-09T21:00:00","screenName":"Sal 2 - Snorre","ticketSaleUrl":"https:\/\/www.nfkino.no\/showtime\/1021\/74876\/","theaterName":"KinoCity","movieVersionId":"MPL20240051"}]},{"mainVersionId":"UIP20221380","title":"Bob Marley: One Love","genres":["Biografi","Drama","Musikkfilm"],"lengthInMinutes":105,"rating":"12 \u00e5r","poster":{"versions":[{"url":"https:\/\/www.filmweb.no\/article1515237.ece\/REPRESENTATIONS\/poster_100x141\/Bob%20Marley:%20One%20Love%20A4"},{"url":"https:\/\/www.filmweb.no\/article1515237.ece\/REPRESENTATIONS\/poster_200x282\/Bob%20Marley:%20One%20Love%20A4"},{"url":"https:\/\/www.filmweb.no\/article1515237.ece\/REPRESENTATIONS\/poster_300x424\/Bob%20Marley:%20One%20Love%20A4"},{"url":"https:\/\/www.filmweb.no\/article1515237.ece\/REPRESENTATIONS\/poster_400x564\/Bob%20Marley:%20One%20Love%20A4"},{"url":"https:\/\/www.filmweb.no\/article1515237.ece\/REPRESENTATIONS\/poster_600x848\/Bob%20Marley:%20One%20Love%20A4"}]},"sanityImagePosterUrl":"https:\/\/cdn.sanity.io\/images\/j0wdmpyb\/production\/9cfd0d1dfb927a48ee7f3d2cf83f64a0b52ceffd-1080x1528.jpg?auto=format","shows":[{"firmName":"KinoCity","showStart":"2024-02-14T20:40:00","screenName":"Sal 1 - Saga","ticketSaleUrl":"https:\/\/www.nfkino.no\/showtime\/1021\/74665\/","theaterName":"KinoCity","movieVersionId":"UIP20221380"},{"firmName":"KinoCity","showStart":"2024-02-15T20:40:00","screenName":"Sal 1 - Saga","ticketSaleUrl":"https:\/\/www.nfkino.no\/showtime\/1021\/75028\/","theaterName":"KinoCity","movieVersionId":"UIP20221380"}]},{"mainVersionId":"NOR20220583","title":"Bukkene Bruse p\u00e5 badeland","genres":["Animasjon","Barnefilm","Komedie"],"lengthInMinutes":70,"rating":"Tillatt for alle","poster":{"versions":[{"url":"https:\/\/www.filmweb.no\/article1516142.ece\/REPRESENTATIONS\/poster_100x141\/Bukkene%20Bruse%20p%C3%A5%20badeland%20Bukkene%20Bruse%20teaserPoster%20staende%20digital.png"},{"url":"https:\/\/www.filmweb.no\/article1516142.ece\/REPRESENTATIONS\/poster_200x282\/Bukkene%20Bruse%20p%C3%A5%20badeland%20Bukkene%20Bruse%20teaserPoster%20staende%20digital.png"},{"url":"https:\/\/www.filmweb.no\/article1516142.ece\/REPRESENTATIONS\/poster_300x424\/Bukkene%20Bruse%20p%C3%A5%20badeland%20Bukkene%20Bruse%20teaserPoster%20staende%20digital.png"},{"url":"https:\/\/www.filmweb.no\/article1516142.ece\/REPRESENTATIONS\/poster_400x564\/Bukkene%20Bruse%20p%C3%A5%20badeland%20Bukkene%20Bruse%20teaserPoster%20staende%20digital.png"},{"url":"https:\/\/www.filmweb.no\/article1516142.ece\/REPRESENTATIONS\/poster_600x848\/Bukkene%20Bruse%20p%C3%A5%20badeland%20Bukkene%20Bruse%20teaserPoster%20staende%20digital.png"}]},"sanityImagePosterUrl":"https:\/\/cdn.sanity.io\/images\/j0wdmpyb\/production\/cad95250db3a19c9a9544cb91037285545ea3657-595x842.jpg?auto=format","shows":[{"firmName":"KinoCity","showStart":"2024-02-08T14:30:00","screenName":"Sal 2 - Snorre","ticketSaleUrl":"https:\/\/www.nfkino.no\/showtime\/1021\/74829\/","theaterName":"KinoCity","movieVersionId":"NOR20220583"},{"firmName":"KinoCity","showStart":"2024-02-08T17:00:00","screenName":"Sal 1 - Saga","ticketSaleUrl":"https:\/\/www.nfkino.no\/showtime\/1021\/74826\/","theaterName":"KinoCity","movieVersionId":"NOR20220583"},{"firmName":"KinoCity","showStart":"2024-02-09T14:30:00","screenName":"Sal 2 - Snorre","ticketSaleUrl":"https:\/\/www.nfkino.no\/showtime\/1021\/74883\/","theaterName":"KinoCity","movieVersionId":"NOR20220583"},{"firmName":"KinoCity","showStart":"2024-02-09T17:00:00","screenName":"Sal 1 - Saga","ticketSaleUrl":"https:\/\/www.nfkino.no\/showtime\/1021\/74880\/","theaterName":"KinoCity","movieVersionId":"NOR20220583"},{"firmName":"KinoCity","showStart":"2024-02-10T12:10:00","screenName":"Sal 1 - Saga","ticketSaleUrl":"https:\/\/www.nfkino.no\/showtime\/1021\/74926\/","theaterName":"KinoCity","movieVersionId":"NOR20220583"},{"firmName":"KinoCity","showStart":"2024-02-10T14:00:00","screenName":"Sal 1 - Saga","ticketSaleUrl":"https:\/\/www.nfkino.no\/showtime\/1021\/74925\/","theaterName":"KinoCity","movieVersionId":"NOR20220583"},{"firmName":"KinoCity","showStart":"2024-02-10T16:10:00","screenName":"Sal 4 - Perfekt","ticketSaleUrl":"https:\/\/www.nfkino.no\/showtime\/1021\/74927\/","theaterName":"KinoCity","movieVersionId":"NOR20220583"},{"firmName":"KinoCity","showStart":"2024-02-11T13:45:00","screenName":"Sal 1 - Saga","ticketSaleUrl":"https:\/\/www.nfkino.no\/showtime\/1021\/74936\/","theaterName":"KinoCity","movieVersionId":"NOR20220583"},{"firmName":"KinoCity","showStart":"2024-02-11T16:10:00","screenName":"Sal 4 - Perfekt","ticketSaleUrl":"https:\/\/www.nfkino.no\/showtime\/1021\/74948\/","theaterName":"KinoCity","movieVersionId":"NOR20220583"},{"firmName":"KinoCity","showStart":"2024-02-12T14:30:00","screenName":"Sal 2 - Snorre","ticketSaleUrl":"https:\/\/www.nfkino.no\/showtime\/1021\/74964\/","theaterName":"KinoCity","movieVersionId":"NOR20220583"},{"firmName":"KinoCity","showStart":"2024-02-12T17:00:00","screenName":"Sal 1 - Saga","ticketSaleUrl":"https:\/\/www.nfkino.no\/showtime\/1021\/74961\/","theaterName":"KinoCity","movieVersionId":"NOR20220583"},{"firmName":"KinoCity","showStart":"2024-02-13T14:30:00","screenName":"Sal 2 - Snorre","ticketSaleUrl":"https:\/\/www.nfkino.no\/showtime\/1021\/74986\/","theaterName":"KinoCity","movieVersionId":"NOR20220583"},{"firmName":"KinoCity","showStart":"2024-02-13T17:00:00","screenName":"Sal 1 - Saga","ticketSaleUrl":"https:\/\/www.nfkino.no\/showtime\/1021\/74983\/","theaterName":"KinoCity","movieVersionId":"NOR20220583"},{"firmName":"KinoCity","showStart":"2024-02-14T14:30:00","screenName":"Sal 2 - Snorre","ticketSaleUrl":"https:\/\/www.nfkino.no\/showtime\/1021\/75005\/","theaterName":"KinoCity","movieVersionId":"NOR20220583"},{"firmName":"KinoCity","showStart":"2024-02-14T16:50:00","screenName":"Sal 4 - Perfekt","ticketSaleUrl":"https:\/\/www.nfkino.no\/showtime\/1021\/75021\/","theaterName":"KinoCity","movieVersionId":"NOR20220583"},{"firmName":"KinoCity","showStart":"2024-02-15T14:30:00","screenName":"Sal 2 - Snorre","ticketSaleUrl":"https:\/\/www.nfkino.no\/showtime\/1021\/75029\/","theaterName":"KinoCity","movieVersionId":"NOR20220583"},{"firmName":"KinoCity","showStart":"2024-02-15T16:50:00","screenName":"Sal 4 - Perfekt","ticketSaleUrl":"https:\/\/www.nfkino.no\/showtime\/1021\/75038\/","theaterName":"KinoCity","movieVersionId":"NOR20220583"}]},{"mainVersionId":"QLT20230928","title":"CARMEN","genres":[],"lengthInMinutes":0,"rating":"","poster":null,"sanityImagePosterUrl":"","shows":[{"firmName":"KinoCity","showStart":"2024-02-19T19:00:00","screenName":"Sal 6 - Kosmorama","ticketSaleUrl":"https:\/\/www.nfkino.no\/showtime\/1021\/71093\/","theaterName":"KinoCity","movieVersionId":"QLT20230928"}]},{"mainVersionId":"FOP20230203","title":"Detektiv Edderkopp","genres":[],"lengthInMinutes":88,"rating":"6 \u00e5r","poster":{"versions":[{"url":"https:\/\/www.filmweb.no\/article1519208.ece\/REPRESENTATIONS\/poster_100x141\/Detektiv%20Edderkopp%20Plakat%20i%20A4-format"},{"url":"https:\/\/www.filmweb.no\/article1519208.ece\/REPRESENTATIONS\/poster_200x282\/Detektiv%20Edderkopp%20Plakat%20i%20A4-format"},{"url":"https:\/\/www.filmweb.no\/article1519208.ece\/REPRESENTATIONS\/poster_300x424\/Detektiv%20Edderkopp%20Plakat%20i%20A4-format"},{"url":"https:\/\/www.filmweb.no\/article1519208.ece\/REPRESENTATIONS\/poster_400x564\/Detektiv%20Edderkopp%20Plakat%20i%20A4-format"},{"url":"https:\/\/www.filmweb.no\/article1519208.ece\/REPRESENTATIONS\/poster_600x848\/Detektiv%20Edderkopp%20Plakat%20i%20A4-format"}]},"sanityImagePosterUrl":"https:\/\/cdn.sanity.io\/images\/j0wdmpyb\/production\/c43fb570454e60cae67a27381e6598b2b7718001-1500x2122.webp?auto=format","shows":[{"firmName":"KinoCity","showStart":"2024-02-09T16:40:00","screenName":"Sal 3 - Palads","ticketSaleUrl":"https:\/\/www.nfkino.no\/showtime\/1021\/74901\/","theaterName":"KinoCity","movieVersionId":"FOP20230203"},{"firmName":"KinoCity","showStart":"2024-02-10T11:30:00","screenName":"Sal 4 - Perfekt","ticketSaleUrl":"https:\/\/www.nfkino.no\/showtime\/1021\/74930\/","theaterName":"KinoCity","movieVersionId":"FOP20230203"},{"firmName":"KinoCity","showStart":"2024-02-10T14:20:00","screenName":"Sal 3 - Palads","ticketSaleUrl":"https:\/\/www.nfkino.no\/showtime\/1021\/74914\/","theaterName":"KinoCity","movieVersionId":"FOP20230203"},{"firmName":"KinoCity","showStart":"2024-02-11T14:20:00","screenName":"Sal 3 - Palads","ticketSaleUrl":"https:\/\/www.nfkino.no\/showtime\/1021\/74943\/","theaterName":"KinoCity","movieVersionId":"FOP20230203"},{"firmName":"KinoCity","showStart":"2024-02-12T16:40:00","screenName":"Sal 3 - Palads","ticketSaleUrl":"https:\/\/www.nfkino.no\/showtime\/1021\/74968\/","theaterName":"KinoCity","movieVersionId":"FOP20230203"},{"firmName":"KinoCity","showStart":"2024-02-13T16:45:00","screenName":"Sal 3 - Palads","ticketSaleUrl":"https:\/\/www.nfkino.no\/showtime\/1021\/74991\/","theaterName":"KinoCity","movieVersionId":"FOP20230203"},{"firmName":"KinoCity","showStart":"2024-02-14T16:45:00","screenName":"Sal 3 - Palads","ticketSaleUrl":"https:\/\/www.nfkino.no\/showtime\/1021\/75024\/","theaterName":"KinoCity","movieVersionId":"FOP20230203"},{"firmName":"KinoCity","showStart":"2024-02-15T16:50:00","screenName":"Sal 3 - Palads","ticketSaleUrl":"https:\/\/www.nfkino.no\/showtime\/1021\/75034\/","theaterName":"KinoCity","movieVersionId":"FOP20230203"}]},{"mainVersionId":"YME20230100","title":"Dream Scenario","genres":["Drama","Komedie","Sort komedie"],"lengthInMinutes":102,"rating":"15 \u00e5r","poster":{"versions":[{"url":"https:\/\/www.filmweb.no\/article1519955.ece\/REPRESENTATIONS\/poster_100x141\/Dream%20Scenario%20DreamScenario_Poster_70x100_NO.jpg"},{"url":"https:\/\/www.filmweb.no\/article1519955.ece\/REPRESENTATIONS\/poster_200x282\/Dream%20Scenario%20DreamScenario_Poster_70x100_NO.jpg"},{"url":"https:\/\/www.filmweb.no\/article1519955.ece\/REPRESENTATIONS\/poster_300x424\/Dream%20Scenario%20DreamScenario_Poster_70x100_NO.jpg"},{"url":"https:\/\/www.filmweb.no\/article1519955.ece\/REPRESENTATIONS\/poster_400x564\/Dream%20Scenario%20DreamScenario_Poster_70x100_NO.jpg"},{"url":"https:\/\/www.filmweb.no\/article1519955.ece\/REPRESENTATIONS\/poster_600x848\/Dream%20Scenario%20DreamScenario_Poster_70x100_NO.jpg"}]},"sanityImagePosterUrl":"https:\/\/cdn.sanity.io\/images\/j0wdmpyb\/production\/4a7a3f8aa1d1ca51bffebba1f02e42bda7558173-1080x1514.jpg?auto=format","shows":[{"firmName":"KinoCity","showStart":"2024-02-08T21:20:00","screenName":"Sal 6 - Kosmorama","ticketSaleUrl":"https:\/\/www.nfkino.no\/showtime\/1021\/74846\/","theaterName":"KinoCity","movieVersionId":"YME20230100"},{"firmName":"KinoCity","showStart":"2024-02-09T14:30:00","screenName":"Sal 6 - Kosmorama","ticketSaleUrl":"https:\/\/www.nfkino.no\/showtime\/1021\/74899\/","theaterName":"KinoCity","movieVersionId":"YME20230100"},{"firmName":"KinoCity","showStart":"2024-02-10T14:30:00","screenName":"Sal 6 - Kosmorama","ticketSaleUrl":"https:\/\/www.nfkino.no\/showtime\/1021\/74923\/","theaterName":"KinoCity","movieVersionId":"YME20230100"},{"firmName":"KinoCity","showStart":"2024-02-11T13:30:00","screenName":"Sal 6 - Kosmorama","ticketSaleUrl":"https:\/\/www.nfkino.no\/showtime\/1021\/74955\/","theaterName":"KinoCity","movieVersionId":"YME20230100"},{"firmName":"KinoCity","showStart":"2024-02-12T14:30:00","screenName":"Sal 6 - Kosmorama","ticketSaleUrl":"https:\/\/www.nfkino.no\/showtime\/1021\/74977\/","theaterName":"KinoCity","movieVersionId":"YME20230100"},{"firmName":"KinoCity","showStart":"2024-02-13T14:30:00","screenName":"Sal 6 - Kosmorama","ticketSaleUrl":"https:\/\/www.nfkino.no\/showtime\/1021\/75000\/","theaterName":"KinoCity","movieVersionId":"YME20230100"},{"firmName":"KinoCity","showStart":"2024-02-14T14:30:00","screenName":"Sal 6 - Kosmorama","ticketSaleUrl":"https:\/\/www.nfkino.no\/showtime\/1021\/75014\/","theaterName":"KinoCity","movieVersionId":"YME20230100"},{"firmName":"KinoCity","showStart":"2024-02-15T14:30:00","screenName":"Sal 6 - Kosmorama","ticketSaleUrl":"https:\/\/www.nfkino.no\/showtime\/1021\/75044\/","theaterName":"KinoCity","movieVersionId":"YME20230100"}]},{"mainVersionId":"SFN20191100","title":"Dune: Part One","genres":["Drama","Eventyr","Sci-Fi"],"lengthInMinutes":155,"rating":"12 \u00e5r","poster":{"versions":[{"url":"https:\/\/www.filmweb.no\/article1466572.ece\/REPRESENTATIONS\/poster_100x141\/Dune%20DUNE_A4_skjerm.jpg"},{"url":"https:\/\/www.filmweb.no\/article1466572.ece\/REPRESENTATIONS\/poster_200x282\/Dune%20DUNE_A4_skjerm.jpg"},{"url":"https:\/\/www.filmweb.no\/article1466572.ece\/REPRESENTATIONS\/poster_300x424\/Dune%20DUNE_A4_skjerm.jpg"},{"url":"https:\/\/www.filmweb.no\/article1466572.ece\/REPRESENTATIONS\/poster_400x564\/Dune%20DUNE_A4_skjerm.jpg"},{"url":"https:\/\/www.filmweb.no\/article1466572.ece\/REPRESENTATIONS\/poster_600x848\/Dune%20DUNE_A4_skjerm.jpg"}]},"sanityImagePosterUrl":"https:\/\/cdn.sanity.io\/images\/j0wdmpyb\/production\/292dc5455b3db9586b07824f021f85be7cde1e39-1000x1415.webp?auto=format","shows":[{"firmName":"KinoCity","showStart":"2024-02-27T16:50:00","screenName":"Sal 1 - Saga","ticketSaleUrl":"https:\/\/www.nfkino.no\/showtime\/1021\/74677\/","theaterName":"KinoCity","movieVersionId":"SFN20191100"}]},{"mainVersionId":"SFN20211456","title":"Dune: Part Two","genres":["Action","Drama","Eventyr","Sci-Fi"],"lengthInMinutes":166,"rating":"12 \u00e5r","poster":{"versions":[{"url":"https:\/\/www.filmweb.no\/article1512595.ece\/REPRESENTATIONS\/poster_100x141\/Dune:%20Part%20Two%20DP2%20teaserplakat"},{"url":"https:\/\/www.filmweb.no\/article1512595.ece\/REPRESENTATIONS\/poster_200x282\/Dune:%20Part%20Two%20DP2%20teaserplakat"},{"url":"https:\/\/www.filmweb.no\/article1512595.ece\/REPRESENTATIONS\/poster_300x424\/Dune:%20Part%20Two%20DP2%20teaserplakat"},{"url":"https:\/\/www.filmweb.no\/article1512595.ece\/REPRESENTATIONS\/poster_400x564\/Dune:%20Part%20Two%20DP2%20teaserplakat"},{"url":"https:\/\/www.filmweb.no\/article1512595.ece\/REPRESENTATIONS\/poster_600x848\/Dune:%20Part%20Two%20DP2%20teaserplakat"}]},"sanityImagePosterUrl":"https:\/\/cdn.sanity.io\/images\/j0wdmpyb\/production\/e83ec0bb540ed5cd76cb02d68845c6832ce59d7f-595x842.jpg?auto=format","shows":[{"firmName":"KinoCity","showStart":"2024-02-27T20:10:00","screenName":"Sal 1 - Saga","ticketSaleUrl":"https:\/\/www.nfkino.no\/showtime\/1021\/74675\/","theaterName":"KinoCity","movieVersionId":"SFN20211456"},{"firmName":"KinoCity","showStart":"2024-02-28T17:20:00","screenName":"Sal 4 - Perfekt","ticketSaleUrl":"https:\/\/www.nfkino.no\/showtime\/1021\/74667\/","theaterName":"KinoCity","movieVersionId":"SFN20211456"},{"firmName":"KinoCity","showStart":"2024-02-28T19:15:00","screenName":"Sal 1 - Saga","ticketSaleUrl":"https:\/\/www.nfkino.no\/showtime\/1021\/74666\/","theaterName":"KinoCity","movieVersionId":"SFN20211456"},{"firmName":"KinoCity","showStart":"2024-02-28T20:45:00","screenName":"Sal 4 - Perfekt","ticketSaleUrl":"https:\/\/www.nfkino.no\/showtime\/1021\/74668\/","theaterName":"KinoCity","movieVersionId":"SFN20211456"},{"firmName":"KinoCity","showStart":"2024-02-29T17:20:00","screenName":"Sal 4 - Perfekt","ticketSaleUrl":"https:\/\/www.nfkino.no\/showtime\/1021\/74863\/","theaterName":"KinoCity","movieVersionId":"SFN20211456"},{"firmName":"KinoCity","showStart":"2024-02-29T19:15:00","screenName":"Sal 1 - Saga","ticketSaleUrl":"https:\/\/www.nfkino.no\/showtime\/1021\/74862\/","theaterName":"KinoCity","movieVersionId":"SFN20211456"},{"firmName":"KinoCity","showStart":"2024-02-29T20:45:00","screenName":"Sal 4 - Perfekt","ticketSaleUrl":"https:\/\/www.nfkino.no\/showtime\/1021\/74864\/","theaterName":"KinoCity","movieVersionId":"SFN20211456"},{"firmName":"KinoCity","showStart":"2024-03-01T17:20:00","screenName":"Sal 4 - Perfekt","ticketSaleUrl":"https:\/\/www.nfkino.no\/showtime\/1021\/74866\/","theaterName":"KinoCity","movieVersionId":"SFN20211456"},{"firmName":"KinoCity","showStart":"2024-03-01T19:15:00","screenName":"Sal 1 - Saga","ticketSaleUrl":"https:\/\/www.nfkino.no\/showtime\/1021\/74865\/","theaterName":"KinoCity","movieVersionId":"SFN20211456"},{"firmName":"KinoCity","showStart":"2024-03-01T20:45:00","screenName":"Sal 4 - Perfekt","ticketSaleUrl":"https:\/\/www.nfkino.no\/showtime\/1021\/74867\/","theaterName":"KinoCity","movieVersionId":"SFN20211456"},{"firmName":"KinoCity","showStart":"2024-03-02T17:20:00","screenName":"Sal 4 - Perfekt","ticketSaleUrl":"https:\/\/www.nfkino.no\/showtime\/1021\/74869\/","theaterName":"KinoCity","movieVersionId":"SFN20211456"},{"firmName":"KinoCity","showStart":"2024-03-02T19:15:00","screenName":"Sal 1 - Saga","ticketSaleUrl":"https:\/\/www.nfkino.no\/showtime\/1021\/74868\/","theaterName":"KinoCity","movieVersionId":"SFN20211456"},{"firmName":"KinoCity","showStart":"2024-03-02T20:45:00","screenName":"Sal 4 - Perfekt","ticketSaleUrl":"https:\/\/www.nfkino.no\/showtime\/1021\/74870\/","theaterName":"KinoCity","movieVersionId":"SFN20211456"},{"firmName":"KinoCity","showStart":"2024-03-03T17:20:00","screenName":"Sal 4 - Perfekt","ticketSaleUrl":"https:\/\/www.nfkino.no\/showtime\/1021\/74871\/","theaterName":"KinoCity","movieVersionId":"SFN20211456"},{"firmName":"KinoCity","showStart":"2024-03-03T19:10:00","screenName":"Sal 1 - Saga","ticketSaleUrl":"https:\/\/www.nfkino.no\/showtime\/1021\/74873\/","theaterName":"KinoCity","movieVersionId":"SFN20211456"},{"firmName":"KinoCity","showStart":"2024-03-03T20:45:00","screenName":"Sal 4 - Perfekt","ticketSaleUrl":"https:\/\/www.nfkino.no\/showtime\/1021\/74872\/","theaterName":"KinoCity","movieVersionId":"SFN20211456"}]},{"mainVersionId":"AWE20230443","title":"Et enkelt liv","genres":["Drama"],"lengthInMinutes":95,"rating":"6 \u00e5r","poster":{"versions":[{"url":"https:\/\/www.filmweb.no\/incoming\/article1518596.ece\/REPRESENTATIONS\/poster_100x141\/Et%20enkelt%20liv"},{"url":"https:\/\/www.filmweb.no\/incoming\/article1518596.ece\/REPRESENTATIONS\/poster_200x282\/Et%20enkelt%20liv"},{"url":"https:\/\/www.filmweb.no\/incoming\/article1518596.ece\/REPRESENTATIONS\/poster_300x424\/Et%20enkelt%20liv"},{"url":"https:\/\/www.filmweb.no\/incoming\/article1518596.ece\/REPRESENTATIONS\/poster_400x564\/Et%20enkelt%20liv"},{"url":"https:\/\/www.filmweb.no\/incoming\/article1518596.ece\/REPRESENTATIONS\/poster_600x848\/Et%20enkelt%20liv"}]},"sanityImagePosterUrl":"https:\/\/cdn.sanity.io\/images\/j0wdmpyb\/production\/475e5dba89e3e355980f424e06493440695afe3b-1240x1772.jpg?auto=format","shows":[{"firmName":"KinoCity","showStart":"2024-02-09T14:30:00","screenName":"Sal 3 - Palads","ticketSaleUrl":"https:\/\/www.nfkino.no\/showtime\/1021\/74902\/","theaterName":"KinoCity","movieVersionId":"AWE20230443"},{"firmName":"KinoCity","showStart":"2024-02-10T16:30:00","screenName":"Sal 3 - Palads","ticketSaleUrl":"https:\/\/www.nfkino.no\/showtime\/1021\/74915\/","theaterName":"KinoCity","movieVersionId":"AWE20230443"},{"firmName":"KinoCity","showStart":"2024-02-11T16:30:00","screenName":"Sal 3 - Palads","ticketSaleUrl":"https:\/\/www.nfkino.no\/showtime\/1021\/74944\/","theaterName":"KinoCity","movieVersionId":"AWE20230443"},{"firmName":"KinoCity","showStart":"2024-02-12T14:30:00","screenName":"Sal 3 - Palads","ticketSaleUrl":"https:\/\/www.nfkino.no\/showtime\/1021\/74967\/","theaterName":"KinoCity","movieVersionId":"AWE20230443"},{"firmName":"KinoCity","showStart":"2024-02-13T18:50:00","screenName":"Sal 6 - Kosmorama","ticketSaleUrl":"https:\/\/www.nfkino.no\/showtime\/1021\/74990\/","theaterName":"KinoCity","movieVersionId":"AWE20230443"},{"firmName":"KinoCity","showStart":"2024-02-14T14:30:00","screenName":"Sal 3 - Palads","ticketSaleUrl":"https:\/\/www.nfkino.no\/showtime\/1021\/75008\/","theaterName":"KinoCity","movieVersionId":"AWE20230443"},{"firmName":"KinoCity","showStart":"2024-02-15T18:50:00","screenName":"Sal 6 - Kosmorama","ticketSaleUrl":"https:\/\/www.nfkino.no\/showtime\/1021\/75033\/","theaterName":"KinoCity","movieVersionId":"AWE20230443"}]},{"mainVersionId":"NOR20210546","title":"H\u00e5ndtering av ud\u00f8de","genres":["Drama"],"lengthInMinutes":97,"rating":"15 \u00e5r","poster":{"versions":[{"url":"https:\/\/www.filmweb.no\/article1519687.ece\/REPRESENTATIONS\/poster_100x141\/H%C3%A5ndtering%20av%20ud%C3%B8de%20A4_skjerm.png"},{"url":"https:\/\/www.filmweb.no\/article1519687.ece\/REPRESENTATIONS\/poster_200x282\/H%C3%A5ndtering%20av%20ud%C3%B8de%20A4_skjerm.png"},{"url":"https:\/\/www.filmweb.no\/article1519687.ece\/REPRESENTATIONS\/poster_300x424\/H%C3%A5ndtering%20av%20ud%C3%B8de%20A4_skjerm.png"},{"url":"https:\/\/www.filmweb.no\/article1519687.ece\/REPRESENTATIONS\/poster_400x564\/H%C3%A5ndtering%20av%20ud%C3%B8de%20A4_skjerm.png"},{"url":"https:\/\/www.filmweb.no\/article1519687.ece\/REPRESENTATIONS\/poster_600x848\/H%C3%A5ndtering%20av%20ud%C3%B8de%20A4_skjerm.png"}]},"sanityImagePosterUrl":"https:\/\/cdn.sanity.io\/images\/j0wdmpyb\/production\/c7c8858e89961e0f8d6761328f28918e01fdc33b-1500x2122.webp?auto=format","shows":[{"firmName":"KinoCity","showStart":"2024-02-09T20:30:00","screenName":"Sal 4 - Perfekt","ticketSaleUrl":"https:\/\/www.nfkino.no\/showtime\/1021\/74903\/","theaterName":"KinoCity","movieVersionId":"NOR20210546"},{"firmName":"KinoCity","showStart":"2024-02-10T20:30:00","screenName":"Sal 4 - Perfekt","ticketSaleUrl":"https:\/\/www.nfkino.no\/showtime\/1021\/74916\/","theaterName":"KinoCity","movieVersionId":"NOR20210546"},{"firmName":"KinoCity","showStart":"2024-02-11T20:30:00","screenName":"Sal 4 - Perfekt","ticketSaleUrl":"https:\/\/www.nfkino.no\/showtime\/1021\/74949\/","theaterName":"KinoCity","movieVersionId":"NOR20210546"},{"firmName":"KinoCity","showStart":"2024-02-12T20:30:00","screenName":"Sal 4 - Perfekt","ticketSaleUrl":"https:\/\/www.nfkino.no\/showtime\/1021\/74972\/","theaterName":"KinoCity","movieVersionId":"NOR20210546"},{"firmName":"KinoCity","showStart":"2024-02-13T11:30:00","screenName":"Sal 5 - Cordial","ticketSaleUrl":"https:\/\/www.nfkino.no\/showtime\/1021\/75049\/","theaterName":"KinoCity","movieVersionId":"NOR20210546"},{"firmName":"KinoCity","showStart":"2024-02-13T20:30:00","screenName":"Sal 4 - Perfekt","ticketSaleUrl":"https:\/\/www.nfkino.no\/showtime\/1021\/74995\/","theaterName":"KinoCity","movieVersionId":"NOR20210546"},{"firmName":"KinoCity","showStart":"2024-02-14T18:40:00","screenName":"Sal 4 - Perfekt","ticketSaleUrl":"https:\/\/www.nfkino.no\/showtime\/1021\/75010\/","theaterName":"KinoCity","movieVersionId":"NOR20210546"},{"firmName":"KinoCity","showStart":"2024-02-15T18:40:00","screenName":"Sal 4 - Perfekt","ticketSaleUrl":"https:\/\/www.nfkino.no\/showtime\/1021\/75039\/","theaterName":"KinoCity","movieVersionId":"NOR20210546"}]},{"mainVersionId":"UAV20237618","title":"Irklais per atlanta","genres":[],"lengthInMinutes":0,"rating":"","poster":null,"sanityImagePosterUrl":"https:\/\/cdn.sanity.io\/images\/j0wdmpyb\/production\/5b5f5cdae4aa88521b1c6e4aa0a77893ff74b8d0-598x884.png?auto=format","shows":[{"firmName":"KinoCity","showStart":"2024-02-10T21:00:00","screenName":"Sal 2 - Snorre","ticketSaleUrl":"https:\/\/www.nfkino.no\/showtime\/1021\/74478\/","theaterName":"KinoCity","movieVersionId":"UAV20237618"}]},{"mainVersionId":"AWE20230433","title":"Jungelgjengen p\u00e5 Verdensturn\u00e9","genres":["Animasjon","Barnefilm","Familiefilm"],"lengthInMinutes":88,"rating":"Tillatt for alle","poster":{"versions":[{"url":"https:\/\/www.filmweb.no\/incoming\/article1516499.ece\/REPRESENTATIONS\/poster_100x141\/Junglebanden"},{"url":"https:\/\/www.filmweb.no\/incoming\/article1516499.ece\/REPRESENTATIONS\/poster_200x282\/Junglebanden"},{"url":"https:\/\/www.filmweb.no\/incoming\/article1516499.ece\/REPRESENTATIONS\/poster_300x424\/Junglebanden"},{"url":"https:\/\/www.filmweb.no\/incoming\/article1516499.ece\/REPRESENTATIONS\/poster_400x564\/Junglebanden"},{"url":"https:\/\/www.filmweb.no\/incoming\/article1516499.ece\/REPRESENTATIONS\/poster_600x848\/Junglebanden"}]},"sanityImagePosterUrl":"https:\/\/cdn.sanity.io\/images\/j0wdmpyb\/production\/bda2ffae69e9a8a2b80a6bde4b298759821f73f4-1500x2143.webp?auto=format","shows":[{"firmName":"KinoCity","showStart":"2024-02-08T16:15:00","screenName":"Sal 2 - Snorre","ticketSaleUrl":"https:\/\/www.nfkino.no\/showtime\/1021\/74830\/","theaterName":"KinoCity","movieVersionId":"AWE20230433"},{"firmName":"KinoCity","showStart":"2024-02-09T16:15:00","screenName":"Sal 2 - Snorre","ticketSaleUrl":"https:\/\/www.nfkino.no\/showtime\/1021\/74884\/","theaterName":"KinoCity","movieVersionId":"AWE20230433"},{"firmName":"KinoCity","showStart":"2024-02-10T12:15:00","screenName":"Sal 3 - Palads","ticketSaleUrl":"https:\/\/www.nfkino.no\/showtime\/1021\/74931\/","theaterName":"KinoCity","movieVersionId":"AWE20230433"},{"firmName":"KinoCity","showStart":"2024-02-10T16:10:00","screenName":"Sal 2 - Snorre","ticketSaleUrl":"https:\/\/www.nfkino.no\/showtime\/1021\/74910\/","theaterName":"KinoCity","movieVersionId":"AWE20230433"},{"firmName":"KinoCity","showStart":"2024-02-11T16:10:00","screenName":"Sal 2 - Snorre","ticketSaleUrl":"https:\/\/www.nfkino.no\/showtime\/1021\/74941\/","theaterName":"KinoCity","movieVersionId":"AWE20230433"},{"firmName":"KinoCity","showStart":"2024-02-12T16:15:00","screenName":"Sal 2 - Snorre","ticketSaleUrl":"https:\/\/www.nfkino.no\/showtime\/1021\/74965\/","theaterName":"KinoCity","movieVersionId":"AWE20230433"},{"firmName":"KinoCity","showStart":"2024-02-13T16:15:00","screenName":"Sal 2 - Snorre","ticketSaleUrl":"https:\/\/www.nfkino.no\/showtime\/1021\/74987\/","theaterName":"KinoCity","movieVersionId":"AWE20230433"},{"firmName":"KinoCity","showStart":"2024-02-14T16:15:00","screenName":"Sal 2 - Snorre","ticketSaleUrl":"https:\/\/www.nfkino.no\/showtime\/1021\/75006\/","theaterName":"KinoCity","movieVersionId":"AWE20230433"},{"firmName":"KinoCity","showStart":"2024-02-15T16:15:00","screenName":"Sal 2 - Snorre","ticketSaleUrl":"https:\/\/www.nfkino.no\/showtime\/1021\/75030\/","theaterName":"KinoCity","movieVersionId":"AWE20230433"}]},{"mainVersionId":"NOR20210544","title":"Konvoi","genres":["Krigsfilm","Spenning"],"lengthInMinutes":108,"rating":"12 \u00e5r","poster":{"versions":[{"url":"https:\/\/www.filmweb.no\/article1518686.ece\/REPRESENTATIONS\/poster_100x141\/Konvoi%20Konvoi_A4_skjerm.jpg"},{"url":"https:\/\/www.filmweb.no\/article1518686.ece\/REPRESENTATIONS\/poster_200x282\/Konvoi%20Konvoi_A4_skjerm.jpg"},{"url":"https:\/\/www.filmweb.no\/article1518686.ece\/REPRESENTATIONS\/poster_300x424\/Konvoi%20Konvoi_A4_skjerm.jpg"},{"url":"https:\/\/www.filmweb.no\/article1518686.ece\/REPRESENTATIONS\/poster_400x564\/Konvoi%20Konvoi_A4_skjerm.jpg"},{"url":"https:\/\/www.filmweb.no\/article1518686.ece\/REPRESENTATIONS\/poster_600x848\/Konvoi%20Konvoi_A4_skjerm.jpg"}]},"sanityImagePosterUrl":"https:\/\/cdn.sanity.io\/images\/j0wdmpyb\/production\/cf7160795a224c0550adc967c9fc346c14e3f411-1240x1754.jpg?auto=format","shows":[{"firmName":"KinoCity","showStart":"2024-02-08T14:30:00","screenName":"Sal 1 - Saga","ticketSaleUrl":"https:\/\/www.nfkino.no\/showtime\/1021\/74825\/","theaterName":"KinoCity","movieVersionId":"NOR20210544"},{"firmName":"KinoCity","showStart":"2024-02-08T18:45:00","screenName":"Sal 1 - Saga","ticketSaleUrl":"https:\/\/www.nfkino.no\/showtime\/1021\/74827\/","theaterName":"KinoCity","movieVersionId":"NOR20210544"},{"firmName":"KinoCity","showStart":"2024-02-09T18:45:00","screenName":"Sal 1 - Saga","ticketSaleUrl":"https:\/\/www.nfkino.no\/showtime\/1021\/74881\/","theaterName":"KinoCity","movieVersionId":"NOR20210544"},{"firmName":"KinoCity","showStart":"2024-02-10T13:35:00","screenName":"Sal 5 - Cordial","ticketSaleUrl":"https:\/\/www.nfkino.no\/showtime\/1021\/75053\/","theaterName":"KinoCity","movieVersionId":"NOR20210544"},{"firmName":"KinoCity","showStart":"2024-02-10T18:30:00","screenName":"Sal 1 - Saga","ticketSaleUrl":"https:\/\/www.nfkino.no\/showtime\/1021\/74907\/","theaterName":"KinoCity","movieVersionId":"NOR20210544"},{"firmName":"KinoCity","showStart":"2024-02-11T13:45:00","screenName":"Sal 5 - Cordial","ticketSaleUrl":"https:\/\/www.nfkino.no\/showtime\/1021\/75054\/","theaterName":"KinoCity","movieVersionId":"NOR20210544"},{"firmName":"KinoCity","showStart":"2024-02-11T18:20:00","screenName":"Sal 1 - Saga","ticketSaleUrl":"https:\/\/www.nfkino.no\/showtime\/1021\/74938\/","theaterName":"KinoCity","movieVersionId":"NOR20210544"},{"firmName":"KinoCity","showStart":"2024-02-12T18:45:00","screenName":"Sal 1 - Saga","ticketSaleUrl":"https:\/\/www.nfkino.no\/showtime\/1021\/74962\/","theaterName":"KinoCity","movieVersionId":"NOR20210544"},{"firmName":"KinoCity","showStart":"2024-02-13T18:45:00","screenName":"Sal 1 - Saga","ticketSaleUrl":"https:\/\/www.nfkino.no\/showtime\/1021\/74984\/","theaterName":"KinoCity","movieVersionId":"NOR20210544"},{"firmName":"KinoCity","showStart":"2024-02-14T18:50:00","screenName":"Sal 3 - Palads","ticketSaleUrl":"https:\/\/www.nfkino.no\/showtime\/1021\/75019\/","theaterName":"KinoCity","movieVersionId":"NOR20210544"},{"firmName":"KinoCity","showStart":"2024-02-15T18:50:00","screenName":"Sal 3 - Palads","ticketSaleUrl":"https:\/\/www.nfkino.no\/showtime\/1021\/75035\/","theaterName":"KinoCity","movieVersionId":"NOR20210544"}]},{"mainVersionId":"QLT20230934","title":"LA RONDINE","genres":[],"lengthInMinutes":0,"rating":"","poster":null,"sanityImagePosterUrl":"","shows":[{"firmName":"KinoCity","showStart":"2024-05-13T19:00:00","screenName":"Sal 6 - Kosmorama","ticketSaleUrl":"https:\/\/www.nfkino.no\/showtime\/1021\/71096\/","theaterName":"KinoCity","movieVersionId":"QLT20230934"}]},{"mainVersionId":"QLT20230930","title":"LA\u00a0FORZA\u00a0DEL\u00a0DESTINO","genres":[],"lengthInMinutes":0,"rating":"","poster":null,"sanityImagePosterUrl":"","shows":[{"firmName":"KinoCity","showStart":"2024-04-01T18:00:00","screenName":"Sal 6 - Kosmorama","ticketSaleUrl":"https:\/\/www.nfkino.no\/showtime\/1021\/71094\/","theaterName":"KinoCity","movieVersionId":"QLT20230930"}]},{"mainVersionId":"SFN20231693","title":"Lassie - P\u00e5 nye eventyr","genres":["Familiefilm"],"lengthInMinutes":92,"rating":"6 \u00e5r","poster":{"versions":[{"url":"https:\/\/www.filmweb.no\/article1518026.ece\/REPRESENTATIONS\/poster_100x141\/Lassie%20-%20P%C3%A5%20nye%20eventyr!%20Lassie_A4_skjerm"},{"url":"https:\/\/www.filmweb.no\/article1518026.ece\/REPRESENTATIONS\/poster_200x282\/Lassie%20-%20P%C3%A5%20nye%20eventyr!%20Lassie_A4_skjerm"},{"url":"https:\/\/www.filmweb.no\/article1518026.ece\/REPRESENTATIONS\/poster_300x424\/Lassie%20-%20P%C3%A5%20nye%20eventyr!%20Lassie_A4_skjerm"},{"url":"https:\/\/www.filmweb.no\/article1518026.ece\/REPRESENTATIONS\/poster_400x564\/Lassie%20-%20P%C3%A5%20nye%20eventyr!%20Lassie_A4_skjerm"},{"url":"https:\/\/www.filmweb.no\/article1518026.ece\/REPRESENTATIONS\/poster_600x848\/Lassie%20-%20P%C3%A5%20nye%20eventyr!%20Lassie_A4_skjerm"}]},"sanityImagePosterUrl":"https:\/\/cdn.sanity.io\/images\/j0wdmpyb\/production\/542a7144bfbbfab2291f531aeb2eb2b99bff0f30-1000x1415.webp?auto=format","shows":[{"firmName":"KinoCity","showStart":"2024-02-08T14:30:00","screenName":"Sal 3 - Palads","ticketSaleUrl":"https:\/\/www.nfkino.no\/showtime\/1021\/74833\/","theaterName":"KinoCity","movieVersionId":"SFN20231693"}]},{"mainVersionId":"QLT20230936","title":"MADAMA BUTTERFLY","genres":[],"lengthInMinutes":0,"rating":"","poster":null,"sanityImagePosterUrl":"","shows":[{"firmName":"KinoCity","showStart":"2024-06-03T19:00:00","screenName":"Sal 6 - Kosmorama","ticketSaleUrl":"https:\/\/www.nfkino.no\/showtime\/1021\/71097\/","theaterName":"KinoCity","movieVersionId":"QLT20230936"}]},{"mainVersionId":"SFN20221537","title":"Madame Web","genres":[],"lengthInMinutes":116,"rating":"12 \u00e5r","poster":{"versions":[{"url":"https:\/\/www.filmweb.no\/article1519935.ece\/REPRESENTATIONS\/poster_100x141\/Madame%20Web%20A4%20skjerm"},{"url":"https:\/\/www.filmweb.no\/article1519935.ece\/REPRESENTATIONS\/poster_200x282\/Madame%20Web%20A4%20skjerm"},{"url":"https:\/\/www.filmweb.no\/article1519935.ece\/REPRESENTATIONS\/poster_300x424\/Madame%20Web%20A4%20skjerm"},{"url":"https:\/\/www.filmweb.no\/article1519935.ece\/REPRESENTATIONS\/poster_400x564\/Madame%20Web%20A4%20skjerm"},{"url":"https:\/\/www.filmweb.no\/article1519935.ece\/REPRESENTATIONS\/poster_600x848\/Madame%20Web%20A4%20skjerm"}]},"sanityImagePosterUrl":"https:\/\/cdn.sanity.io\/images\/j0wdmpyb\/production\/58bd873f5820cd87398e57786cd398122ee8d5c0-1240x1754.jpg?auto=format","shows":[{"firmName":"KinoCity","showStart":"2024-02-14T18:00:00","screenName":"Sal 1 - Saga","ticketSaleUrl":"https:\/\/www.nfkino.no\/showtime\/1021\/74802\/","theaterName":"KinoCity","movieVersionId":"SFN20221537"},{"firmName":"KinoCity","showStart":"2024-02-15T18:00:00","screenName":"Sal 1 - Saga","ticketSaleUrl":"https:\/\/www.nfkino.no\/showtime\/1021\/75027\/","theaterName":"KinoCity","movieVersionId":"SFN20221537"}]},{"mainVersionId":"UIP20231606","title":"Mean Girls","genres":["Komedie","Musikal"],"lengthInMinutes":112,"rating":"9 \u00e5r","poster":{"versions":[{"url":"https:\/\/www.filmweb.no\/article1519058.ece\/REPRESENTATIONS\/poster_100x141\/Mean%20Girls%20A4"},{"url":"https:\/\/www.filmweb.no\/article1519058.ece\/REPRESENTATIONS\/poster_200x282\/Mean%20Girls%20A4"},{"url":"https:\/\/www.filmweb.no\/article1519058.ece\/REPRESENTATIONS\/poster_300x424\/Mean%20Girls%20A4"},{"url":"https:\/\/www.filmweb.no\/article1519058.ece\/REPRESENTATIONS\/poster_400x564\/Mean%20Girls%20A4"},{"url":"https:\/\/www.filmweb.no\/article1519058.ece\/REPRESENTATIONS\/poster_600x848\/Mean%20Girls%20A4"}]},"sanityImagePosterUrl":"https:\/\/cdn.sanity.io\/images\/j0wdmpyb\/production\/e8de9b00d2ac96222d43717c96db4ac6ff46b779-1500x2122.webp?auto=format","shows":[{"firmName":"KinoCity","showStart":"2024-02-08T19:00:00","screenName":"Sal 3 - Palads","ticketSaleUrl":"https:\/\/www.nfkino.no\/showtime\/1021\/74835\/","theaterName":"KinoCity","movieVersionId":"UIP20231606"},{"firmName":"KinoCity","showStart":"2024-02-09T18:45:00","screenName":"Sal 3 - Palads","ticketSaleUrl":"https:\/\/www.nfkino.no\/showtime\/1021\/74888\/","theaterName":"KinoCity","movieVersionId":"UIP20231606"},{"firmName":"KinoCity","showStart":"2024-02-10T18:45:00","screenName":"Sal 3 - Palads","ticketSaleUrl":"https:\/\/www.nfkino.no\/showtime\/1021\/74912\/","theaterName":"KinoCity","movieVersionId":"UIP20231606"},{"firmName":"KinoCity","showStart":"2024-02-11T18:45:00","screenName":"Sal 3 - Palads","ticketSaleUrl":"https:\/\/www.nfkino.no\/showtime\/1021\/74945\/","theaterName":"KinoCity","movieVersionId":"UIP20231606"},{"firmName":"KinoCity","showStart":"2024-02-12T18:50:00","screenName":"Sal 3 - Palads","ticketSaleUrl":"https:\/\/www.nfkino.no\/showtime\/1021\/74969\/","theaterName":"KinoCity","movieVersionId":"UIP20231606"},{"firmName":"KinoCity","showStart":"2024-02-13T18:50:00","screenName":"Sal 3 - Palads","ticketSaleUrl":"https:\/\/www.nfkino.no\/showtime\/1021\/74992\/","theaterName":"KinoCity","movieVersionId":"UIP20231606"},{"firmName":"KinoCity","showStart":"2024-02-15T21:00:00","screenName":"Sal 2 - Snorre","ticketSaleUrl":"https:\/\/www.nfkino.no\/showtime\/1021\/75032\/","theaterName":"KinoCity","movieVersionId":"UIP20231606"}]},{"mainVersionId":"MER20230084","title":"Mirakelet i Gullsp\u00e5ng","genres":["Dokumentar"],"lengthInMinutes":107,"rating":"12 \u00e5r","poster":{"versions":[{"url":"https:\/\/www.filmweb.no\/article1519662.ece\/REPRESENTATIONS\/poster_100x141\/Mirakelet%20i%20Gullsp%C3%A5ng%20MIRAKELET%20I%20GULLSP%C3%85NG%20-%20A4.jpg"},{"url":"https:\/\/www.filmweb.no\/article1519662.ece\/REPRESENTATIONS\/poster_200x282\/Mirakelet%20i%20Gullsp%C3%A5ng%20MIRAKELET%20I%20GULLSP%C3%85NG%20-%20A4.jpg"},{"url":"https:\/\/www.filmweb.no\/article1519662.ece\/REPRESENTATIONS\/poster_300x424\/Mirakelet%20i%20Gullsp%C3%A5ng%20MIRAKELET%20I%20GULLSP%C3%85NG%20-%20A4.jpg"},{"url":"https:\/\/www.filmweb.no\/article1519662.ece\/REPRESENTATIONS\/poster_400x564\/Mirakelet%20i%20Gullsp%C3%A5ng%20MIRAKELET%20I%20GULLSP%C3%85NG%20-%20A4.jpg"},{"url":"https:\/\/www.filmweb.no\/article1519662.ece\/REPRESENTATIONS\/poster_600x848\/Mirakelet%20i%20Gullsp%C3%A5ng%20MIRAKELET%20I%20GULLSP%C3%85NG%20-%20A4.jpg"}]},"sanityImagePosterUrl":"https:\/\/cdn.sanity.io\/images\/j0wdmpyb\/production\/a7a044131612124688690a8453fe25c17680a1ee-1500x2143.webp?auto=format","shows":[{"firmName":"KinoCity","showStart":"2024-02-08T18:00:00","screenName":"Sal 5 - Cordial","ticketSaleUrl":"https:\/\/www.nfkino.no\/showtime\/1021\/74841\/","theaterName":"KinoCity","movieVersionId":"MER20230084"},{"firmName":"KinoCity","showStart":"2024-02-09T18:10:00","screenName":"Sal 5 - Cordial","ticketSaleUrl":"https:\/\/www.nfkino.no\/showtime\/1021\/74894\/","theaterName":"KinoCity","movieVersionId":"MER20230084"},{"firmName":"KinoCity","showStart":"2024-02-10T12:00:00","screenName":"Sal 6 - Kosmorama","ticketSaleUrl":"https:\/\/www.nfkino.no\/showtime\/1021\/74934\/","theaterName":"KinoCity","movieVersionId":"MER20230084"},{"firmName":"KinoCity","showStart":"2024-02-10T18:15:00","screenName":"Sal 5 - Cordial","ticketSaleUrl":"https:\/\/www.nfkino.no\/showtime\/1021\/74919\/","theaterName":"KinoCity","movieVersionId":"MER20230084"},{"firmName":"KinoCity","showStart":"2024-02-11T18:30:00","screenName":"Sal 5 - Cordial","ticketSaleUrl":"https:\/\/www.nfkino.no\/showtime\/1021\/74953\/","theaterName":"KinoCity","movieVersionId":"MER20230084"},{"firmName":"KinoCity","showStart":"2024-02-12T18:00:00","screenName":"Sal 5 - Cordial","ticketSaleUrl":"https:\/\/www.nfkino.no\/showtime\/1021\/74975\/","theaterName":"KinoCity","movieVersionId":"MER20230084"},{"firmName":"KinoCity","showStart":"2024-02-13T11:30:00","screenName":"Sal 1 - Saga","ticketSaleUrl":"https:\/\/www.nfkino.no\/showtime\/1021\/75050\/","theaterName":"KinoCity","movieVersionId":"MER20230084"},{"firmName":"KinoCity","showStart":"2024-02-13T18:00:00","screenName":"Sal 5 - Cordial","ticketSaleUrl":"https:\/\/www.nfkino.no\/showtime\/1021\/74998\/","theaterName":"KinoCity","movieVersionId":"MER20230084"},{"firmName":"KinoCity","showStart":"2024-02-14T18:00:00","screenName":"Sal 5 - Cordial","ticketSaleUrl":"https:\/\/www.nfkino.no\/showtime\/1021\/75012\/","theaterName":"KinoCity","movieVersionId":"MER20230084"},{"firmName":"KinoCity","showStart":"2024-02-15T18:00:00","screenName":"Sal 5 - Cordial","ticketSaleUrl":"https:\/\/www.nfkino.no\/showtime\/1021\/75042\/","theaterName":"KinoCity","movieVersionId":"MER20230084"}]},{"mainVersionId":"ART20230574","title":"Perfect Days","genres":["Drama"],"lengthInMinutes":124,"rating":"Tillatt for alle","poster":{"versions":[{"url":"https:\/\/www.filmweb.no\/article1519870.ece\/REPRESENTATIONS\/poster_100x141\/Perfect%20Days%20Perfect%20Days%20-%20norsk%20plakat"},{"url":"https:\/\/www.filmweb.no\/article1519870.ece\/REPRESENTATIONS\/poster_200x282\/Perfect%20Days%20Perfect%20Days%20-%20norsk%20plakat"},{"url":"https:\/\/www.filmweb.no\/article1519870.ece\/REPRESENTATIONS\/poster_300x424\/Perfect%20Days%20Perfect%20Days%20-%20norsk%20plakat"},{"url":"https:\/\/www.filmweb.no\/article1519870.ece\/REPRESENTATIONS\/poster_400x564\/Perfect%20Days%20Perfect%20Days%20-%20norsk%20plakat"},{"url":"https:\/\/www.filmweb.no\/article1519870.ece\/REPRESENTATIONS\/poster_600x848\/Perfect%20Days%20Perfect%20Days%20-%20norsk%20plakat"}]},"sanityImagePosterUrl":"https:\/\/cdn.sanity.io\/images\/j0wdmpyb\/production\/92617266d6fbbafbada457a2da5761cb45000cea-1500x2143.webp?auto=format","shows":[{"firmName":"KinoCity","showStart":"2024-02-08T15:15:00","screenName":"Sal 5 - Cordial","ticketSaleUrl":"https:\/\/www.nfkino.no\/showtime\/1021\/74840\/","theaterName":"KinoCity","movieVersionId":"ART20230574"},{"firmName":"KinoCity","showStart":"2024-02-09T15:20:00","screenName":"Sal 5 - Cordial","ticketSaleUrl":"https:\/\/www.nfkino.no\/showtime\/1021\/74893\/","theaterName":"KinoCity","movieVersionId":"ART20230574"},{"firmName":"KinoCity","showStart":"2024-02-10T20:45:00","screenName":"Sal 5 - Cordial","ticketSaleUrl":"https:\/\/www.nfkino.no\/showtime\/1021\/74918\/","theaterName":"KinoCity","movieVersionId":"ART20230574"},{"firmName":"KinoCity","showStart":"2024-02-11T21:00:00","screenName":"Sal 5 - Cordial","ticketSaleUrl":"https:\/\/www.nfkino.no\/showtime\/1021\/74954\/","theaterName":"KinoCity","movieVersionId":"ART20230574"},{"firmName":"KinoCity","showStart":"2024-02-12T15:15:00","screenName":"Sal 5 - Cordial","ticketSaleUrl":"https:\/\/www.nfkino.no\/showtime\/1021\/74974\/","theaterName":"KinoCity","movieVersionId":"ART20230574"},{"firmName":"KinoCity","showStart":"2024-02-13T21:00:00","screenName":"Sal 6 - Kosmorama","ticketSaleUrl":"https:\/\/www.nfkino.no\/showtime\/1021\/74997\/","theaterName":"KinoCity","movieVersionId":"ART20230574"},{"firmName":"KinoCity","showStart":"2024-02-14T15:15:00","screenName":"Sal 5 - Cordial","ticketSaleUrl":"https:\/\/www.nfkino.no\/showtime\/1021\/75011\/","theaterName":"KinoCity","movieVersionId":"ART20230574"},{"firmName":"KinoCity","showStart":"2024-02-15T21:00:00","screenName":"Sal 6 - Kosmorama","ticketSaleUrl":"https:\/\/www.nfkino.no\/showtime\/1021\/75041\/","theaterName":"KinoCity","movieVersionId":"ART20230574"}]},{"mainVersionId":"BVI20200539","title":"Poor Things","genres":["Coming of age","Drama","Eksperimentell","Komedie"],"lengthInMinutes":141,"rating":"15 \u00e5r","poster":{"versions":[{"url":"https:\/\/www.filmweb.no\/article1516831.ece\/REPRESENTATIONS\/poster_100x141\/Poor%20Things%20Payoff"},{"url":"https:\/\/www.filmweb.no\/article1516831.ece\/REPRESENTATIONS\/poster_200x282\/Poor%20Things%20Payoff"},{"url":"https:\/\/www.filmweb.no\/article1516831.ece\/REPRESENTATIONS\/poster_300x424\/Poor%20Things%20Payoff"},{"url":"https:\/\/www.filmweb.no\/article1516831.ece\/REPRESENTATIONS\/poster_400x564\/Poor%20Things%20Payoff"},{"url":"https:\/\/www.filmweb.no\/article1516831.ece\/REPRESENTATIONS\/poster_600x848\/Poor%20Things%20Payoff"}]},"sanityImagePosterUrl":"https:\/\/cdn.sanity.io\/images\/j0wdmpyb\/production\/cd1cf83aee4fcd9d51f2388aa9e14fd58bc5ec65-1500x2143.webp?auto=format","shows":[{"firmName":"KinoCity","showStart":"2024-02-08T21:00:00","screenName":"Sal 2 - Snorre","ticketSaleUrl":"https:\/\/www.nfkino.no\/showtime\/1021\/74832\/","theaterName":"KinoCity","movieVersionId":"BVI20200539"},{"firmName":"KinoCity","showStart":"2024-02-11T21:00:00","screenName":"Sal 2 - Snorre","ticketSaleUrl":"https:\/\/www.nfkino.no\/showtime\/1021\/74959\/","theaterName":"KinoCity","movieVersionId":"BVI20200539"},{"firmName":"KinoCity","showStart":"2024-02-12T21:00:00","screenName":"Sal 2 - Snorre","ticketSaleUrl":"https:\/\/www.nfkino.no\/showtime\/1021\/74981\/","theaterName":"KinoCity","movieVersionId":"BVI20200539"},{"firmName":"KinoCity","showStart":"2024-02-13T21:00:00","screenName":"Sal 2 - Snorre","ticketSaleUrl":"https:\/\/www.nfkino.no\/showtime\/1021\/74989\/","theaterName":"KinoCity","movieVersionId":"BVI20200539"}]},{"mainVersionId":"QLT20230932","title":"ROM\u00c9O ET JULIETTE","genres":[],"lengthInMinutes":0,"rating":"","poster":null,"sanityImagePosterUrl":"","shows":[{"firmName":"KinoCity","showStart":"2024-04-15T19:00:00","screenName":"Sal 6 - Kosmorama","ticketSaleUrl":"https:\/\/www.nfkino.no\/showtime\/1021\/71095\/","theaterName":"KinoCity","movieVersionId":"QLT20230932"}]},{"mainVersionId":"NFD20230381","title":"Sau","genres":["Dokumentar"],"lengthInMinutes":83,"rating":"9 \u00e5r","poster":{"versions":[{"url":"https:\/\/www.filmweb.no\/article1519968.ece\/REPRESENTATIONS\/poster_100x141\/Sau%201080x1920-1.jpg"},{"url":"https:\/\/www.filmweb.no\/article1519968.ece\/REPRESENTATIONS\/poster_200x282\/Sau%201080x1920-1.jpg"},{"url":"https:\/\/www.filmweb.no\/article1519968.ece\/REPRESENTATIONS\/poster_300x424\/Sau%201080x1920-1.jpg"},{"url":"https:\/\/www.filmweb.no\/article1519968.ece\/REPRESENTATIONS\/poster_400x564\/Sau%201080x1920-1.jpg"},{"url":"https:\/\/www.filmweb.no\/article1519968.ece\/REPRESENTATIONS\/poster_600x848\/Sau%201080x1920-1.jpg"}]},"sanityImagePosterUrl":"https:\/\/cdn.sanity.io\/images\/j0wdmpyb\/production\/c3137afb22fb051e2d717c3fc1b17e7955439bbb-1080x1920.jpg?auto=format","shows":[{"firmName":"KinoCity","showStart":"2024-02-08T17:00:00","screenName":"Sal 6 - Kosmorama","ticketSaleUrl":"https:\/\/www.nfkino.no\/showtime\/1021\/74857\/","theaterName":"KinoCity","movieVersionId":"NFD20230381"},{"firmName":"KinoCity","showStart":"2024-02-09T16:50:00","screenName":"Sal 6 - Kosmorama","ticketSaleUrl":"https:\/\/www.nfkino.no\/showtime\/1021\/74897\/","theaterName":"KinoCity","movieVersionId":"NFD20230381"},{"firmName":"KinoCity","showStart":"2024-02-10T16:50:00","screenName":"Sal 6 - Kosmorama","ticketSaleUrl":"https:\/\/www.nfkino.no\/showtime\/1021\/74921\/","theaterName":"KinoCity","movieVersionId":"NFD20230381"},{"firmName":"KinoCity","showStart":"2024-02-11T16:00:00","screenName":"Sal 6 - Kosmorama","ticketSaleUrl":"https:\/\/www.nfkino.no\/showtime\/1021\/74956\/","theaterName":"KinoCity","movieVersionId":"NFD20230381"},{"firmName":"KinoCity","showStart":"2024-02-12T16:50:00","screenName":"Sal 6 - Kosmorama","ticketSaleUrl":"https:\/\/www.nfkino.no\/showtime\/1021\/74978\/","theaterName":"KinoCity","movieVersionId":"NFD20230381"},{"firmName":"KinoCity","showStart":"2024-02-13T16:50:00","screenName":"Sal 6 - Kosmorama","ticketSaleUrl":"https:\/\/www.nfkino.no\/showtime\/1021\/75001\/","theaterName":"KinoCity","movieVersionId":"NFD20230381"},{"firmName":"KinoCity","showStart":"2024-02-14T16:50:00","screenName":"Sal 6 - Kosmorama","ticketSaleUrl":"https:\/\/www.nfkino.no\/showtime\/1021\/75015\/","theaterName":"KinoCity","movieVersionId":"NFD20230381"},{"firmName":"KinoCity","showStart":"2024-02-15T16:50:00","screenName":"Sal 6 - Kosmorama","ticketSaleUrl":"https:\/\/www.nfkino.no\/showtime\/1021\/75045\/","theaterName":"KinoCity","movieVersionId":"NFD20230381"}]},{"mainVersionId":"YME20230077","title":"Superkompisene","genres":["Animasjon","Barnefilm","Familiefilm"],"lengthInMinutes":90,"rating":"6 \u00e5r","poster":{"versions":[{"url":"https:\/\/www.filmweb.no\/article1520061.ece\/REPRESENTATIONS\/poster_100x141\/Superkompisene%20TheInseparables_Poster_70x100_Credit_NO.jpg"},{"url":"https:\/\/www.filmweb.no\/article1520061.ece\/REPRESENTATIONS\/poster_200x282\/Superkompisene%20TheInseparables_Poster_70x100_Credit_NO.jpg"},{"url":"https:\/\/www.filmweb.no\/article1520061.ece\/REPRESENTATIONS\/poster_300x424\/Superkompisene%20TheInseparables_Poster_70x100_Credit_NO.jpg"},{"url":"https:\/\/www.filmweb.no\/article1520061.ece\/REPRESENTATIONS\/poster_400x564\/Superkompisene%20TheInseparables_Poster_70x100_Credit_NO.jpg"},{"url":"https:\/\/www.filmweb.no\/article1520061.ece\/REPRESENTATIONS\/poster_600x848\/Superkompisene%20TheInseparables_Poster_70x100_Credit_NO.jpg"}]},"sanityImagePosterUrl":"https:\/\/cdn.sanity.io\/images\/j0wdmpyb\/production\/98f8807f33858a71158b7273ffc1712ed915b8af-1500x2143.webp?auto=format","shows":[{"firmName":"KinoCity","showStart":"2024-02-08T16:50:00","screenName":"Sal 3 - Palads","ticketSaleUrl":"https:\/\/www.nfkino.no\/showtime\/1021\/74834\/","theaterName":"KinoCity","movieVersionId":"YME20230077"},{"firmName":"KinoCity","showStart":"2024-02-09T15:50:00","screenName":"Sal 4 - Perfekt","ticketSaleUrl":"https:\/\/www.nfkino.no\/showtime\/1021\/74887\/","theaterName":"KinoCity","movieVersionId":"YME20230077"},{"firmName":"KinoCity","showStart":"2024-02-10T11:30:00","screenName":"Sal 5 - Cordial","ticketSaleUrl":"https:\/\/www.nfkino.no\/showtime\/1021\/74932\/","theaterName":"KinoCity","movieVersionId":"YME20230077"},{"firmName":"KinoCity","showStart":"2024-02-10T14:00:00","screenName":"Sal 2 - Snorre","ticketSaleUrl":"https:\/\/www.nfkino.no\/showtime\/1021\/74928\/","theaterName":"KinoCity","movieVersionId":"YME20230077"},{"firmName":"KinoCity","showStart":"2024-02-11T14:00:00","screenName":"Sal 2 - Snorre","ticketSaleUrl":"https:\/\/www.nfkino.no\/showtime\/1021\/74940\/","theaterName":"KinoCity","movieVersionId":"YME20230077"},{"firmName":"KinoCity","showStart":"2024-02-12T15:50:00","screenName":"Sal 4 - Perfekt","ticketSaleUrl":"https:\/\/www.nfkino.no\/showtime\/1021\/74971\/","theaterName":"KinoCity","movieVersionId":"YME20230077"},{"firmName":"KinoCity","showStart":"2024-02-13T15:50:00","screenName":"Sal 4 - Perfekt","ticketSaleUrl":"https:\/\/www.nfkino.no\/showtime\/1021\/74994\/","theaterName":"KinoCity","movieVersionId":"YME20230077"}]},{"mainVersionId":"BOL20240814","title":"Teri Baaton Mein Aisa Uljha Jiya","genres":["Komedie","Romantikk","Sci-Fi"],"lengthInMinutes":141,"rating":"6 \u00e5r","poster":null,"sanityImagePosterUrl":"https:\/\/cdn.sanity.io\/images\/j0wdmpyb\/production\/520bac6205eb39c03f43e778284ca257b70217bb-819x1024.jpg?auto=format","shows":[{"firmName":"KinoCity","showStart":"2024-02-14T21:00:00","screenName":"Sal 2 - Snorre","ticketSaleUrl":"https:\/\/www.nfkino.no\/showtime\/1021\/75057\/","theaterName":"KinoCity","movieVersionId":"BOL20240814"}]},{"mainVersionId":"YME20230105","title":"The Beekeeper","genres":["Action"],"lengthInMinutes":105,"rating":"15 \u00e5r","poster":{"versions":[{"url":"https:\/\/www.filmweb.no\/article1518773.ece\/REPRESENTATIONS\/poster_100x141\/The%20Beekeeper%20TheBeekeeper_Poster_70x100_NO.jpg"},{"url":"https:\/\/www.filmweb.no\/article1518773.ece\/REPRESENTATIONS\/poster_200x282\/The%20Beekeeper%20TheBeekeeper_Poster_70x100_NO.jpg"},{"url":"https:\/\/www.filmweb.no\/article1518773.ece\/REPRESENTATIONS\/poster_300x424\/The%20Beekeeper%20TheBeekeeper_Poster_70x100_NO.jpg"},{"url":"https:\/\/www.filmweb.no\/article1518773.ece\/REPRESENTATIONS\/poster_400x564\/The%20Beekeeper%20TheBeekeeper_Poster_70x100_NO.jpg"},{"url":"https:\/\/www.filmweb.no\/article1518773.ece\/REPRESENTATIONS\/poster_600x848\/The%20Beekeeper%20TheBeekeeper_Poster_70x100_NO.jpg"}]},"sanityImagePosterUrl":"https:\/\/cdn.sanity.io\/images\/j0wdmpyb\/production\/0f8162617910c752a808ad0411ff0b4271858469-1000x1429.webp?auto=format","shows":[{"firmName":"KinoCity","showStart":"2024-02-09T21:10:00","screenName":"Sal 1 - Saga","ticketSaleUrl":"https:\/\/www.nfkino.no\/showtime\/1021\/74906\/","theaterName":"KinoCity","movieVersionId":"YME20230105"},{"firmName":"KinoCity","showStart":"2024-02-10T21:00:00","screenName":"Sal 1 - Saga","ticketSaleUrl":"https:\/\/www.nfkino.no\/showtime\/1021\/74909\/","theaterName":"KinoCity","movieVersionId":"YME20230105"},{"firmName":"KinoCity","showStart":"2024-02-11T20:50:00","screenName":"Sal 1 - Saga","ticketSaleUrl":"https:\/\/www.nfkino.no\/showtime\/1021\/74939\/","theaterName":"KinoCity","movieVersionId":"YME20230105"},{"firmName":"KinoCity","showStart":"2024-02-12T21:10:00","screenName":"Sal 1 - Saga","ticketSaleUrl":"https:\/\/www.nfkino.no\/showtime\/1021\/74963\/","theaterName":"KinoCity","movieVersionId":"YME20230105"},{"firmName":"KinoCity","showStart":"2024-02-13T21:10:00","screenName":"Sal 1 - Saga","ticketSaleUrl":"https:\/\/www.nfkino.no\/showtime\/1021\/74985\/","theaterName":"KinoCity","movieVersionId":"YME20230105"},{"firmName":"KinoCity","showStart":"2024-02-14T21:00:00","screenName":"Sal 4 - Perfekt","ticketSaleUrl":"https:\/\/www.nfkino.no\/showtime\/1021\/75020\/","theaterName":"KinoCity","movieVersionId":"YME20230105"},{"firmName":"KinoCity","showStart":"2024-02-15T21:00:00","screenName":"Sal 4 - Perfekt","ticketSaleUrl":"https:\/\/www.nfkino.no\/showtime\/1021\/75040\/","theaterName":"KinoCity","movieVersionId":"YME20230105"}]},{"mainVersionId":"SFN20211333","title":"The Color Purple","genres":["Drama"],"lengthInMinutes":140,"rating":"12 \u00e5r","poster":{"versions":[{"url":"https:\/\/www.filmweb.no\/incoming\/article1519089.ece\/REPRESENTATIONS\/poster_100x141\/The%20Color%20Purple"},{"url":"https:\/\/www.filmweb.no\/incoming\/article1519089.ece\/REPRESENTATIONS\/poster_200x282\/The%20Color%20Purple"},{"url":"https:\/\/www.filmweb.no\/incoming\/article1519089.ece\/REPRESENTATIONS\/poster_300x424\/The%20Color%20Purple"},{"url":"https:\/\/www.filmweb.no\/incoming\/article1519089.ece\/REPRESENTATIONS\/poster_400x564\/The%20Color%20Purple"},{"url":"https:\/\/www.filmweb.no\/incoming\/article1519089.ece\/REPRESENTATIONS\/poster_600x848\/The%20Color%20Purple"}]},"sanityImagePosterUrl":"https:\/\/cdn.sanity.io\/images\/j0wdmpyb\/production\/5e4383664c54a0be94f2b1067cda7c9f8d59a077-1500x2223.webp?auto=format","shows":[{"firmName":"KinoCity","showStart":"2024-02-08T14:50:00","screenName":"Sal 4 - Perfekt","ticketSaleUrl":"https:\/\/www.nfkino.no\/showtime\/1021\/74837\/","theaterName":"KinoCity","movieVersionId":"SFN20211333"}]},{"mainVersionId":"UIP20231587","title":"The Holdovers","genres":["Drama"],"lengthInMinutes":133,"rating":"9 \u00e5r","poster":{"versions":[{"url":"https:\/\/www.filmweb.no\/article1519604.ece\/REPRESENTATIONS\/poster_100x141\/The%20Holdovers%20A4"},{"url":"https:\/\/www.filmweb.no\/article1519604.ece\/REPRESENTATIONS\/poster_200x282\/The%20Holdovers%20A4"},{"url":"https:\/\/www.filmweb.no\/article1519604.ece\/REPRESENTATIONS\/poster_300x424\/The%20Holdovers%20A4"},{"url":"https:\/\/www.filmweb.no\/article1519604.ece\/REPRESENTATIONS\/poster_400x564\/The%20Holdovers%20A4"},{"url":"https:\/\/www.filmweb.no\/article1519604.ece\/REPRESENTATIONS\/poster_600x848\/The%20Holdovers%20A4"}]},"sanityImagePosterUrl":"https:\/\/cdn.sanity.io\/images\/j0wdmpyb\/production\/1cf022f1c816f3fc2267be77f42016410f6db6dd-1500x2122.webp?auto=format","shows":[{"firmName":"KinoCity","showStart":"2024-02-08T20:30:00","screenName":"Sal 5 - Cordial","ticketSaleUrl":"https:\/\/www.nfkino.no\/showtime\/1021\/74842\/","theaterName":"KinoCity","movieVersionId":"UIP20231587"},{"firmName":"KinoCity","showStart":"2024-02-09T21:15:00","screenName":"Sal 6 - Kosmorama","ticketSaleUrl":"https:\/\/www.nfkino.no\/showtime\/1021\/74895\/","theaterName":"KinoCity","movieVersionId":"UIP20231587"},{"firmName":"KinoCity","showStart":"2024-02-10T21:15:00","screenName":"Sal 6 - Kosmorama","ticketSaleUrl":"https:\/\/www.nfkino.no\/showtime\/1021\/74924\/","theaterName":"KinoCity","movieVersionId":"UIP20231587"},{"firmName":"KinoCity","showStart":"2024-02-11T20:30:00","screenName":"Sal 6 - Kosmorama","ticketSaleUrl":"https:\/\/www.nfkino.no\/showtime\/1021\/74958\/","theaterName":"KinoCity","movieVersionId":"UIP20231587"},{"firmName":"KinoCity","showStart":"2024-02-12T21:15:00","screenName":"Sal 6 - Kosmorama","ticketSaleUrl":"https:\/\/www.nfkino.no\/showtime\/1021\/74980\/","theaterName":"KinoCity","movieVersionId":"UIP20231587"},{"firmName":"KinoCity","showStart":"2024-02-13T11:30:00","screenName":"Sal 4 - Perfekt","ticketSaleUrl":"https:\/\/www.nfkino.no\/showtime\/1021\/75052\/","theaterName":"KinoCity","movieVersionId":"UIP20231587"},{"firmName":"KinoCity","showStart":"2024-02-13T15:10:00","screenName":"Sal 5 - Cordial","ticketSaleUrl":"https:\/\/www.nfkino.no\/showtime\/1021\/75003\/","theaterName":"KinoCity","movieVersionId":"UIP20231587"},{"firmName":"KinoCity","showStart":"2024-02-14T21:15:00","screenName":"Sal 6 - Kosmorama","ticketSaleUrl":"https:\/\/www.nfkino.no\/showtime\/1021\/75017\/","theaterName":"KinoCity","movieVersionId":"UIP20231587"},{"firmName":"KinoCity","showStart":"2024-02-15T15:10:00","screenName":"Sal 5 - Cordial","ticketSaleUrl":"https:\/\/www.nfkino.no\/showtime\/1021\/75047\/","theaterName":"KinoCity","movieVersionId":"UIP20231587"}]},{"mainVersionId":"SFN20231697","title":"The Zone of Interest","genres":["Drama"],"lengthInMinutes":105,"rating":"12 \u00e5r","poster":{"versions":[{"url":"https:\/\/www.filmweb.no\/article1518717.ece\/REPRESENTATIONS\/poster_100x141\/The%20Zone%20of%20Interest%20A4_skjerm%20-%20Teaser"},{"url":"https:\/\/www.filmweb.no\/article1518717.ece\/REPRESENTATIONS\/poster_200x282\/The%20Zone%20of%20Interest%20A4_skjerm%20-%20Teaser"},{"url":"https:\/\/www.filmweb.no\/article1518717.ece\/REPRESENTATIONS\/poster_300x424\/The%20Zone%20of%20Interest%20A4_skjerm%20-%20Teaser"},{"url":"https:\/\/www.filmweb.no\/article1518717.ece\/REPRESENTATIONS\/poster_400x564\/The%20Zone%20of%20Interest%20A4_skjerm%20-%20Teaser"},{"url":"https:\/\/www.filmweb.no\/article1518717.ece\/REPRESENTATIONS\/poster_600x848\/The%20Zone%20of%20Interest%20A4_skjerm%20-%20Teaser"}]},"sanityImagePosterUrl":"https:\/\/cdn.sanity.io\/images\/j0wdmpyb\/production\/e5bf1f9f5a41ff606cd0bd10ad87ba9ce2b544d1-1000x1415.webp?auto=format","shows":[{"firmName":"KinoCity","showStart":"2024-02-08T14:30:00","screenName":"Sal 6 - Kosmorama","ticketSaleUrl":"https:\/\/www.nfkino.no\/showtime\/1021\/74843\/","theaterName":"KinoCity","movieVersionId":"SFN20231697"},{"firmName":"KinoCity","showStart":"2024-02-08T19:00:00","screenName":"Sal 6 - Kosmorama","ticketSaleUrl":"https:\/\/www.nfkino.no\/showtime\/1021\/74845\/","theaterName":"KinoCity","movieVersionId":"SFN20231697"},{"firmName":"KinoCity","showStart":"2024-02-09T18:50:00","screenName":"Sal 6 - Kosmorama","ticketSaleUrl":"https:\/\/www.nfkino.no\/showtime\/1021\/74898\/","theaterName":"KinoCity","movieVersionId":"SFN20231697"},{"firmName":"KinoCity","showStart":"2024-02-10T18:50:00","screenName":"Sal 6 - Kosmorama","ticketSaleUrl":"https:\/\/www.nfkino.no\/showtime\/1021\/74922\/","theaterName":"KinoCity","movieVersionId":"SFN20231697"},{"firmName":"KinoCity","showStart":"2024-02-11T18:00:00","screenName":"Sal 6 - Kosmorama","ticketSaleUrl":"https:\/\/www.nfkino.no\/showtime\/1021\/74957\/","theaterName":"KinoCity","movieVersionId":"SFN20231697"},{"firmName":"KinoCity","showStart":"2024-02-12T18:50:00","screenName":"Sal 6 - Kosmorama","ticketSaleUrl":"https:\/\/www.nfkino.no\/showtime\/1021\/74979\/","theaterName":"KinoCity","movieVersionId":"SFN20231697"},{"firmName":"KinoCity","showStart":"2024-02-13T14:30:00","screenName":"Sal 3 - Palads","ticketSaleUrl":"https:\/\/www.nfkino.no\/showtime\/1021\/75002\/","theaterName":"KinoCity","movieVersionId":"SFN20231697"},{"firmName":"KinoCity","showStart":"2024-02-14T18:50:00","screenName":"Sal 6 - Kosmorama","ticketSaleUrl":"https:\/\/www.nfkino.no\/showtime\/1021\/75016\/","theaterName":"KinoCity","movieVersionId":"SFN20231697"},{"firmName":"KinoCity","showStart":"2024-02-15T14:30:00","screenName":"Sal 3 - Palads","ticketSaleUrl":"https:\/\/www.nfkino.no\/showtime\/1021\/75046\/","theaterName":"KinoCity","movieVersionId":"SFN20231697"}]},{"mainVersionId":"NFD20230370","title":"Tundraens voktere - Eallogierdu","genres":["Drama"],"lengthInMinutes":95,"rating":"12 \u00e5r","poster":{"versions":[{"url":"https:\/\/www.filmweb.no\/article1520121.ece\/REPRESENTATIONS\/poster_100x141\/Tundraens%20voktere%20Tundraens%20voktere%20-%20Eallogierdu"},{"url":"https:\/\/www.filmweb.no\/article1520121.ece\/REPRESENTATIONS\/poster_200x282\/Tundraens%20voktere%20Tundraens%20voktere%20-%20Eallogierdu"},{"url":"https:\/\/www.filmweb.no\/article1520121.ece\/REPRESENTATIONS\/poster_300x424\/Tundraens%20voktere%20Tundraens%20voktere%20-%20Eallogierdu"},{"url":"https:\/\/www.filmweb.no\/article1520121.ece\/REPRESENTATIONS\/poster_400x564\/Tundraens%20voktere%20Tundraens%20voktere%20-%20Eallogierdu"},{"url":"https:\/\/www.filmweb.no\/article1520121.ece\/REPRESENTATIONS\/poster_600x848\/Tundraens%20voktere%20Tundraens%20voktere%20-%20Eallogierdu"}]},"sanityImagePosterUrl":"https:\/\/cdn.sanity.io\/images\/j0wdmpyb\/production\/d92fddb35c292176eb0b0b1a3347f2028816f2dc-1500x2143.webp?auto=format","shows":[{"firmName":"KinoCity","showStart":"2024-02-09T20:45:00","screenName":"Sal 5 - Cordial","ticketSaleUrl":"https:\/\/www.nfkino.no\/showtime\/1021\/74905\/","theaterName":"KinoCity","movieVersionId":"NFD20230370"},{"firmName":"KinoCity","showStart":"2024-02-10T16:00:00","screenName":"Sal 5 - Cordial","ticketSaleUrl":"https:\/\/www.nfkino.no\/showtime\/1021\/74920\/","theaterName":"KinoCity","movieVersionId":"NFD20230370"},{"firmName":"KinoCity","showStart":"2024-02-11T16:15:00","screenName":"Sal 5 - Cordial","ticketSaleUrl":"https:\/\/www.nfkino.no\/showtime\/1021\/74952\/","theaterName":"KinoCity","movieVersionId":"NFD20230370"},{"firmName":"KinoCity","showStart":"2024-02-12T20:30:00","screenName":"Sal 5 - Cordial","ticketSaleUrl":"https:\/\/www.nfkino.no\/showtime\/1021\/74976\/","theaterName":"KinoCity","movieVersionId":"NFD20230370"},{"firmName":"KinoCity","showStart":"2024-02-13T11:30:00","screenName":"Sal 6 - Kosmorama","ticketSaleUrl":"https:\/\/www.nfkino.no\/showtime\/1021\/75048\/","theaterName":"KinoCity","movieVersionId":"NFD20230370"},{"firmName":"KinoCity","showStart":"2024-02-13T20:30:00","screenName":"Sal 5 - Cordial","ticketSaleUrl":"https:\/\/www.nfkino.no\/showtime\/1021\/74999\/","theaterName":"KinoCity","movieVersionId":"NFD20230370"},{"firmName":"KinoCity","showStart":"2024-02-14T20:30:00","screenName":"Sal 5 - Cordial","ticketSaleUrl":"https:\/\/www.nfkino.no\/showtime\/1021\/75013\/","theaterName":"KinoCity","movieVersionId":"NFD20230370"},{"firmName":"KinoCity","showStart":"2024-02-15T20:30:00","screenName":"Sal 5 - Cordial","ticketSaleUrl":"https:\/\/www.nfkino.no\/showtime\/1021\/75043\/","theaterName":"KinoCity","movieVersionId":"NFD20230370"}]},{"mainVersionId":"AWE20230452","title":"Vermin","genres":["Action","Gr\u00f8sser","Horror","Skrekkfilm"],"lengthInMinutes":103,"rating":"15 \u00e5r","poster":null,"sanityImagePosterUrl":"https:\/\/cdn.sanity.io\/images\/j0wdmpyb\/production\/3c1be4bbda34bf417778babf23ce6284ff1ace90-1500x2143.webp?auto=format","shows":[{"firmName":"KinoCity","showStart":"2024-02-08T21:30:00","screenName":"Sal 3 - Palads","ticketSaleUrl":"https:\/\/www.nfkino.no\/showtime\/1021\/74836\/","theaterName":"KinoCity","movieVersionId":"AWE20230452"}]},{"mainVersionId":"SFN20211337","title":"Wonka","genres":["Familiefilm"],"lengthInMinutes":116,"rating":"6 \u00e5r","poster":{"versions":[{"url":"https:\/\/www.filmweb.no\/article1519209.ece\/REPRESENTATIONS\/poster_100x141\/Wonka%20Wonka%20hovedplakat%20A4.jpg"},{"url":"https:\/\/www.filmweb.no\/article1519209.ece\/REPRESENTATIONS\/poster_200x282\/Wonka%20Wonka%20hovedplakat%20A4.jpg"},{"url":"https:\/\/www.filmweb.no\/article1519209.ece\/REPRESENTATIONS\/poster_300x424\/Wonka%20Wonka%20hovedplakat%20A4.jpg"},{"url":"https:\/\/www.filmweb.no\/article1519209.ece\/REPRESENTATIONS\/poster_400x564\/Wonka%20Wonka%20hovedplakat%20A4.jpg"},{"url":"https:\/\/www.filmweb.no\/article1519209.ece\/REPRESENTATIONS\/poster_600x848\/Wonka%20Wonka%20hovedplakat%20A4.jpg"}]},"sanityImagePosterUrl":"https:\/\/cdn.sanity.io\/images\/j0wdmpyb\/production\/64ccaf10250bb0cbbd41b21a4c9767ab0c374760-595x842.jpg?auto=format","shows":[{"firmName":"KinoCity","showStart":"2024-02-08T17:50:00","screenName":"Sal 4 - Perfekt","ticketSaleUrl":"https:\/\/www.nfkino.no\/showtime\/1021\/74838\/","theaterName":"KinoCity","movieVersionId":"WAB20230188"},{"firmName":"KinoCity","showStart":"2024-02-08T18:20:00","screenName":"Sal 2 - Snorre","ticketSaleUrl":"https:\/\/www.nfkino.no\/showtime\/1021\/74831\/","theaterName":"KinoCity","movieVersionId":"SFN20211337"},{"firmName":"KinoCity","showStart":"2024-02-09T14:30:00","screenName":"Sal 1 - Saga","ticketSaleUrl":"https:\/\/www.nfkino.no\/showtime\/1021\/74891\/","theaterName":"KinoCity","movieVersionId":"WAB20230188"},{"firmName":"KinoCity","showStart":"2024-02-09T18:20:00","screenName":"Sal 2 - Snorre","ticketSaleUrl":"https:\/\/www.nfkino.no\/showtime\/1021\/74885\/","theaterName":"KinoCity","movieVersionId":"SFN20211337"},{"firmName":"KinoCity","showStart":"2024-02-10T11:30:00","screenName":"Sal 2 - Snorre","ticketSaleUrl":"https:\/\/www.nfkino.no\/showtime\/1021\/74935\/","theaterName":"KinoCity","movieVersionId":"WAB20230188"},{"firmName":"KinoCity","showStart":"2024-02-10T13:35:00","screenName":"Sal 4 - Perfekt","ticketSaleUrl":"https:\/\/www.nfkino.no\/showtime\/1021\/74929\/","theaterName":"KinoCity","movieVersionId":"WAB20230188"},{"firmName":"KinoCity","showStart":"2024-02-10T15:50:00","screenName":"Sal 1 - Saga","ticketSaleUrl":"https:\/\/www.nfkino.no\/showtime\/1021\/74908\/","theaterName":"KinoCity","movieVersionId":"WAB20230188"},{"firmName":"KinoCity","showStart":"2024-02-10T18:20:00","screenName":"Sal 2 - Snorre","ticketSaleUrl":"https:\/\/www.nfkino.no\/showtime\/1021\/74911\/","theaterName":"KinoCity","movieVersionId":"SFN20211337"},{"firmName":"KinoCity","showStart":"2024-02-11T13:30:00","screenName":"Sal 4 - Perfekt","ticketSaleUrl":"https:\/\/www.nfkino.no\/showtime\/1021\/74947\/","theaterName":"KinoCity","movieVersionId":"WAB20230188"},{"firmName":"KinoCity","showStart":"2024-02-11T15:40:00","screenName":"Sal 1 - Saga","ticketSaleUrl":"https:\/\/www.nfkino.no\/showtime\/1021\/74937\/","theaterName":"KinoCity","movieVersionId":"WAB20230188"},{"firmName":"KinoCity","showStart":"2024-02-11T18:20:00","screenName":"Sal 2 - Snorre","ticketSaleUrl":"https:\/\/www.nfkino.no\/showtime\/1021\/74942\/","theaterName":"KinoCity","movieVersionId":"SFN20211337"},{"firmName":"KinoCity","showStart":"2024-02-12T14:30:00","screenName":"Sal 1 - Saga","ticketSaleUrl":"https:\/\/www.nfkino.no\/showtime\/1021\/74960\/","theaterName":"KinoCity","movieVersionId":"WAB20230188"},{"firmName":"KinoCity","showStart":"2024-02-12T18:20:00","screenName":"Sal 2 - Snorre","ticketSaleUrl":"https:\/\/www.nfkino.no\/showtime\/1021\/74966\/","theaterName":"KinoCity","movieVersionId":"SFN20211337"},{"firmName":"KinoCity","showStart":"2024-02-13T14:30:00","screenName":"Sal 1 - Saga","ticketSaleUrl":"https:\/\/www.nfkino.no\/showtime\/1021\/74982\/","theaterName":"KinoCity","movieVersionId":"WAB20230188"},{"firmName":"KinoCity","showStart":"2024-02-13T18:20:00","screenName":"Sal 2 - Snorre","ticketSaleUrl":"https:\/\/www.nfkino.no\/showtime\/1021\/74988\/","theaterName":"KinoCity","movieVersionId":"SFN20211337"},{"firmName":"KinoCity","showStart":"2024-02-14T15:20:00","screenName":"Sal 1 - Saga","ticketSaleUrl":"https:\/\/www.nfkino.no\/showtime\/1021\/75004\/","theaterName":"KinoCity","movieVersionId":"WAB20230188"},{"firmName":"KinoCity","showStart":"2024-02-14T18:20:00","screenName":"Sal 2 - Snorre","ticketSaleUrl":"https:\/\/www.nfkino.no\/showtime\/1021\/75007\/","theaterName":"KinoCity","movieVersionId":"SFN20211337"},{"firmName":"KinoCity","showStart":"2024-02-15T15:20:00","screenName":"Sal 1 - Saga","ticketSaleUrl":"https:\/\/www.nfkino.no\/showtime\/1021\/75026\/","theaterName":"KinoCity","movieVersionId":"WAB20230188"},{"firmName":"KinoCity","showStart":"2024-02-15T18:20:00","screenName":"Sal 2 - Snorre","ticketSaleUrl":"https:\/\/www.nfkino.no\/showtime\/1021\/75031\/","theaterName":"KinoCity","movieVersionId":"SFN20211337"}]}]