[{"mainVersionId":"BVI20230764","title":"All of us Strangers","genres":["Drama","Romantikk"],"lengthInMinutes":105,"rating":"12 \u00e5r","poster":{"versions":[{"url":"https:\/\/www.filmweb.no\/article1519670.ece\/REPRESENTATIONS\/poster_100x141\/All%20of%20us%20Strangers%20Plakat"},{"url":"https:\/\/www.filmweb.no\/article1519670.ece\/REPRESENTATIONS\/poster_200x282\/All%20of%20us%20Strangers%20Plakat"},{"url":"https:\/\/www.filmweb.no\/article1519670.ece\/REPRESENTATIONS\/poster_300x424\/All%20of%20us%20Strangers%20Plakat"},{"url":"https:\/\/www.filmweb.no\/article1519670.ece\/REPRESENTATIONS\/poster_400x564\/All%20of%20us%20Strangers%20Plakat"},{"url":"https:\/\/www.filmweb.no\/article1519670.ece\/REPRESENTATIONS\/poster_600x848\/All%20of%20us%20Strangers%20Plakat"}]},"sanityImagePosterUrl":"https:\/\/cdn.sanity.io\/images\/j0wdmpyb\/production\/d68f1904ef76567569063491f943b58d9fdbaca1-1500x2143.webp?auto=format","shows":[{"firmName":"Sandnes Kino","showStart":"2024-02-14T20:30:00","screenName":"Sal 6 LUXE","ticketSaleUrl":"https:\/\/www.odeonkino.no\/api\/v2\/redirect\/show\/Sys99-NO\/700be473-51e4-4592-a7f2-7081b5893de0","theaterName":"Sandnes Kino","movieVersionId":"BVI20230764"}]},{"mainVersionId":"SFN20211464","title":"Anyone But You","genres":[],"lengthInMinutes":103,"rating":"12 \u00e5r","poster":{"versions":[{"url":"https:\/\/www.filmweb.no\/article1518767.ece\/REPRESENTATIONS\/poster_100x141\/Anyone%20But%20You%20A4%20skjerm%20-%20Teaser"},{"url":"https:\/\/www.filmweb.no\/article1518767.ece\/REPRESENTATIONS\/poster_200x282\/Anyone%20But%20You%20A4%20skjerm%20-%20Teaser"},{"url":"https:\/\/www.filmweb.no\/article1518767.ece\/REPRESENTATIONS\/poster_300x424\/Anyone%20But%20You%20A4%20skjerm%20-%20Teaser"},{"url":"https:\/\/www.filmweb.no\/article1518767.ece\/REPRESENTATIONS\/poster_400x564\/Anyone%20But%20You%20A4%20skjerm%20-%20Teaser"},{"url":"https:\/\/www.filmweb.no\/article1518767.ece\/REPRESENTATIONS\/poster_600x848\/Anyone%20But%20You%20A4%20skjerm%20-%20Teaser"}]},"sanityImagePosterUrl":"https:\/\/cdn.sanity.io\/images\/j0wdmpyb\/production\/4ca32bf8c509d0c9d25a3162e0a646ee0865921d-1240x1754.jpg?auto=format","shows":[{"firmName":"Sandnes Kino","showStart":"2024-02-08T20:00:00","screenName":"Sal 3 Sandnes","ticketSaleUrl":"https:\/\/www.odeonkino.no\/api\/v2\/redirect\/show\/Sys99-NO\/0f976a75-02ad-488b-b820-64fb1be7b846","theaterName":"Sandnes Kino","movieVersionId":"SFN20211464"},{"firmName":"Sandnes Kino","showStart":"2024-02-09T18:00:00","screenName":"Sal 3 Sandnes","ticketSaleUrl":"https:\/\/www.odeonkino.no\/api\/v2\/redirect\/show\/Sys99-NO\/25ae9be8-e22a-49ee-a4e2-9b151dd16b8a","theaterName":"Sandnes Kino","movieVersionId":"SFN20211464"},{"firmName":"Sandnes Kino","showStart":"2024-02-10T18:30:00","screenName":"Sal 3 Sandnes","ticketSaleUrl":"https:\/\/www.odeonkino.no\/api\/v2\/redirect\/show\/Sys99-NO\/d8d51339-6c55-46de-a0b5-071e1b1e9a59","theaterName":"Sandnes Kino","movieVersionId":"SFN20211464"},{"firmName":"Sandnes Kino","showStart":"2024-02-10T21:00:00","screenName":"Sal 3 Sandnes","ticketSaleUrl":"https:\/\/www.odeonkino.no\/api\/v2\/redirect\/show\/Sys99-NO\/65ba8ed5-d75f-49dc-b276-5c05401f344e","theaterName":"Sandnes Kino","movieVersionId":"SFN20231708"},{"firmName":"Sandnes Kino","showStart":"2024-02-11T18:00:00","screenName":"Sal 3 Sandnes","ticketSaleUrl":"https:\/\/www.odeonkino.no\/api\/v2\/redirect\/show\/Sys99-NO\/aaad0733-aca1-4c3c-914b-a44b605a56af","theaterName":"Sandnes Kino","movieVersionId":"SFN20211464"},{"firmName":"Sandnes Kino","showStart":"2024-02-11T20:30:00","screenName":"Sal 3 Sandnes","ticketSaleUrl":"https:\/\/www.odeonkino.no\/api\/v2\/redirect\/show\/Sys99-NO\/a7e617db-747f-4519-9708-91c7efce3427","theaterName":"Sandnes Kino","movieVersionId":"SFN20231708"},{"firmName":"Sandnes Kino","showStart":"2024-02-13T18:30:00","screenName":"Sal 3 Sandnes","ticketSaleUrl":"https:\/\/www.odeonkino.no\/api\/v2\/redirect\/show\/Sys99-NO\/72120235-8049-4534-a629-ac6db2625d93","theaterName":"Sandnes Kino","movieVersionId":"SFN20211464"},{"firmName":"Sandnes Kino","showStart":"2024-02-22T19:00:00","screenName":"Sal 7 - VIP","ticketSaleUrl":"https:\/\/www.odeonkino.no\/api\/v2\/redirect\/show\/Sys99-NO\/46aa0590-c969-46a7-934c-0f962107bf57","theaterName":"Sandnes Kino","movieVersionId":"SFN20211464"},{"firmName":"Sandnes Kino","showStart":"2024-02-22T19:00:00","screenName":"Sal 6 LUXE","ticketSaleUrl":"https:\/\/www.odeonkino.no\/api\/v2\/redirect\/show\/Sys99-NO\/bd491b9a-7b2f-4bd0-8182-d546da9b3c83","theaterName":"Sandnes Kino","movieVersionId":"SFN20211464"}]},{"mainVersionId":"UIP20231595","title":"Argylle","genres":["Action","Thriller"],"lengthInMinutes":139,"rating":"12 \u00e5r","poster":{"versions":[{"url":"https:\/\/www.filmweb.no\/article1517690.ece\/REPRESENTATIONS\/poster_100x141\/Argylle%20Midlertidig%20thumbnail%20for%20Filmweb"},{"url":"https:\/\/www.filmweb.no\/article1517690.ece\/REPRESENTATIONS\/poster_200x282\/Argylle%20Midlertidig%20thumbnail%20for%20Filmweb"},{"url":"https:\/\/www.filmweb.no\/article1517690.ece\/REPRESENTATIONS\/poster_300x424\/Argylle%20Midlertidig%20thumbnail%20for%20Filmweb"},{"url":"https:\/\/www.filmweb.no\/article1517690.ece\/REPRESENTATIONS\/poster_400x564\/Argylle%20Midlertidig%20thumbnail%20for%20Filmweb"},{"url":"https:\/\/www.filmweb.no\/article1517690.ece\/REPRESENTATIONS\/poster_600x848\/Argylle%20Midlertidig%20thumbnail%20for%20Filmweb"}]},"sanityImagePosterUrl":"https:\/\/cdn.sanity.io\/images\/j0wdmpyb\/production\/d2e337648b29e34d5bdce432b988a0a8c9950a1b-1500x2122.webp?auto=format","shows":[{"firmName":"Sandnes Kino","showStart":"2024-02-08T17:45:00","screenName":"Sal 1 - isense by BATE","ticketSaleUrl":"https:\/\/www.odeonkino.no\/api\/v2\/redirect\/show\/Sys99-NO\/b99c244f-f5bd-41f3-ba68-f708fe3b9b35","theaterName":"Sandnes Kino","movieVersionId":"UIP20231618"},{"firmName":"Sandnes Kino","showStart":"2024-02-08T20:45:00","screenName":"Sal 1 - isense by BATE","ticketSaleUrl":"https:\/\/www.odeonkino.no\/api\/v2\/redirect\/show\/Sys99-NO\/9efed395-c112-4765-90c2-c7a4aff5bfc0","theaterName":"Sandnes Kino","movieVersionId":"UIP20231618"},{"firmName":"Sandnes Kino","showStart":"2024-02-09T21:15:00","screenName":"Sal 5 Sandnes","ticketSaleUrl":"https:\/\/www.odeonkino.no\/api\/v2\/redirect\/show\/Sys99-NO\/b228f325-ca1a-4059-9739-5396cc65b989","theaterName":"Sandnes Kino","movieVersionId":"UIP20231595"},{"firmName":"Sandnes Kino","showStart":"2024-02-10T20:45:00","screenName":"Sal 5 Sandnes","ticketSaleUrl":"https:\/\/www.odeonkino.no\/api\/v2\/redirect\/show\/Sys99-NO\/4d9e1303-80ab-4288-9725-14d9216e4374","theaterName":"Sandnes Kino","movieVersionId":"UIP20231595"},{"firmName":"Sandnes Kino","showStart":"2024-02-11T20:15:00","screenName":"Sal 5 Sandnes","ticketSaleUrl":"https:\/\/www.odeonkino.no\/api\/v2\/redirect\/show\/Sys99-NO\/c7ac9273-da3e-48d1-99c8-6baa62a8f523","theaterName":"Sandnes Kino","movieVersionId":"UIP20231595"},{"firmName":"Sandnes Kino","showStart":"2024-02-12T20:15:00","screenName":"Sal 5 Sandnes","ticketSaleUrl":"https:\/\/www.odeonkino.no\/api\/v2\/redirect\/show\/Sys99-NO\/7b644edb-71c5-462a-aac7-769cc8db174a","theaterName":"Sandnes Kino","movieVersionId":"UIP20231595"},{"firmName":"Sandnes Kino","showStart":"2024-02-13T20:15:00","screenName":"Sal 5 Sandnes","ticketSaleUrl":"https:\/\/www.odeonkino.no\/api\/v2\/redirect\/show\/Sys99-NO\/bddac2c7-e70c-46c7-b2f4-a4b9ca3f4674","theaterName":"Sandnes Kino","movieVersionId":"UIP20231595"}]},{"mainVersionId":"UIP20221380","title":"Bob Marley: One Love","genres":["Biografi","Drama","Musikkfilm"],"lengthInMinutes":105,"rating":"12 \u00e5r","poster":{"versions":[{"url":"https:\/\/www.filmweb.no\/article1515237.ece\/REPRESENTATIONS\/poster_100x141\/Bob%20Marley:%20One%20Love%20A4"},{"url":"https:\/\/www.filmweb.no\/article1515237.ece\/REPRESENTATIONS\/poster_200x282\/Bob%20Marley:%20One%20Love%20A4"},{"url":"https:\/\/www.filmweb.no\/article1515237.ece\/REPRESENTATIONS\/poster_300x424\/Bob%20Marley:%20One%20Love%20A4"},{"url":"https:\/\/www.filmweb.no\/article1515237.ece\/REPRESENTATIONS\/poster_400x564\/Bob%20Marley:%20One%20Love%20A4"},{"url":"https:\/\/www.filmweb.no\/article1515237.ece\/REPRESENTATIONS\/poster_600x848\/Bob%20Marley:%20One%20Love%20A4"}]},"sanityImagePosterUrl":"https:\/\/cdn.sanity.io\/images\/j0wdmpyb\/production\/9cfd0d1dfb927a48ee7f3d2cf83f64a0b52ceffd-1080x1528.jpg?auto=format","shows":[{"firmName":"Sandnes Kino","showStart":"2024-02-14T18:30:00","screenName":"Sal 3 Sandnes","ticketSaleUrl":"https:\/\/www.odeonkino.no\/api\/v2\/redirect\/show\/Sys99-NO\/65a81aab-7f0b-4ce5-a20c-eafb0565fd6e","theaterName":"Sandnes Kino","movieVersionId":"UIP20231619"},{"firmName":"Sandnes Kino","showStart":"2024-02-15T12:30:00","screenName":"Sal 6 LUXE","ticketSaleUrl":"https:\/\/www.odeonkino.no\/api\/v2\/redirect\/show\/Sys99-NO\/4ecac2bd-2b54-45b0-a79c-c357ff46cf8b","theaterName":"Sandnes Kino","movieVersionId":"UIP20221380"},{"firmName":"Sandnes Kino","showStart":"2024-02-15T18:30:00","screenName":"Sal 3 Sandnes","ticketSaleUrl":"https:\/\/www.odeonkino.no\/api\/v2\/redirect\/show\/Sys99-NO\/72fccaf7-8c79-4ce7-826b-21f0150fca3a","theaterName":"Sandnes Kino","movieVersionId":"UIP20231619"}]},{"mainVersionId":"NOR20220583","title":"Bukkene Bruse p\u00e5 badeland","genres":["Animasjon","Barnefilm","Komedie"],"lengthInMinutes":70,"rating":"Tillatt for alle","poster":{"versions":[{"url":"https:\/\/www.filmweb.no\/article1516142.ece\/REPRESENTATIONS\/poster_100x141\/Bukkene%20Bruse%20p%C3%A5%20badeland%20Bukkene%20Bruse%20teaserPoster%20staende%20digital.png"},{"url":"https:\/\/www.filmweb.no\/article1516142.ece\/REPRESENTATIONS\/poster_200x282\/Bukkene%20Bruse%20p%C3%A5%20badeland%20Bukkene%20Bruse%20teaserPoster%20staende%20digital.png"},{"url":"https:\/\/www.filmweb.no\/article1516142.ece\/REPRESENTATIONS\/poster_300x424\/Bukkene%20Bruse%20p%C3%A5%20badeland%20Bukkene%20Bruse%20teaserPoster%20staende%20digital.png"},{"url":"https:\/\/www.filmweb.no\/article1516142.ece\/REPRESENTATIONS\/poster_400x564\/Bukkene%20Bruse%20p%C3%A5%20badeland%20Bukkene%20Bruse%20teaserPoster%20staende%20digital.png"},{"url":"https:\/\/www.filmweb.no\/article1516142.ece\/REPRESENTATIONS\/poster_600x848\/Bukkene%20Bruse%20p%C3%A5%20badeland%20Bukkene%20Bruse%20teaserPoster%20staende%20digital.png"}]},"sanityImagePosterUrl":"https:\/\/cdn.sanity.io\/images\/j0wdmpyb\/production\/cad95250db3a19c9a9544cb91037285545ea3657-595x842.jpg?auto=format","shows":[{"firmName":"Sandnes Kino","showStart":"2024-02-09T16:45:00","screenName":"Sal 7 - VIP","ticketSaleUrl":"https:\/\/www.odeonkino.no\/api\/v2\/redirect\/show\/Sys99-NO\/308ae920-e519-4944-a5b4-ecb0212e5c38","theaterName":"Sandnes Kino","movieVersionId":"NOR20220583"},{"firmName":"Sandnes Kino","showStart":"2024-02-10T10:45:00","screenName":"Sal 1 - isense by BATE","ticketSaleUrl":"https:\/\/www.odeonkino.no\/api\/v2\/redirect\/show\/Sys99-NO\/aee8dd6b-5ebe-4658-af72-41f882f8aa56","theaterName":"Sandnes Kino","movieVersionId":"NOR20220583"},{"firmName":"Sandnes Kino","showStart":"2024-02-10T12:35:00","screenName":"Sal 1 - isense by BATE","ticketSaleUrl":"https:\/\/www.odeonkino.no\/api\/v2\/redirect\/show\/Sys99-NO\/5e70fe13-8849-49fc-afdb-cff9f0f26daa","theaterName":"Sandnes Kino","movieVersionId":"NOR20220583"},{"firmName":"Sandnes Kino","showStart":"2024-02-10T14:25:00","screenName":"Sal 1 - isense by BATE","ticketSaleUrl":"https:\/\/www.odeonkino.no\/api\/v2\/redirect\/show\/Sys99-NO\/0384a92e-6573-4449-86ef-334f33598ea8","theaterName":"Sandnes Kino","movieVersionId":"NOR20220583"},{"firmName":"Sandnes Kino","showStart":"2024-02-11T12:30:00","screenName":"Sal 1 - isense by BATE","ticketSaleUrl":"https:\/\/www.odeonkino.no\/api\/v2\/redirect\/show\/Sys99-NO\/b1606b96-ab18-4e19-8cd0-bd59a8def6e0","theaterName":"Sandnes Kino","movieVersionId":"NOR20220583"},{"firmName":"Sandnes Kino","showStart":"2024-02-11T14:30:00","screenName":"Sal 1 - isense by BATE","ticketSaleUrl":"https:\/\/www.odeonkino.no\/api\/v2\/redirect\/show\/Sys99-NO\/58d33d41-e500-4a15-9268-9731b54c50f5","theaterName":"Sandnes Kino","movieVersionId":"NOR20220583"},{"firmName":"Sandnes Kino","showStart":"2024-02-11T16:30:00","screenName":"Sal 1 - isense by BATE","ticketSaleUrl":"https:\/\/www.odeonkino.no\/api\/v2\/redirect\/show\/Sys99-NO\/a5958bb8-f323-4852-9f8c-79b6f91b66c2","theaterName":"Sandnes Kino","movieVersionId":"NOR20220583"}]},{"mainVersionId":"SFN20191136","title":"Dark Windows","genres":["Skrekkfilm"],"lengthInMinutes":78,"rating":"15 \u00e5r","poster":{"versions":[{"url":"https:\/\/www.filmweb.no\/article1515565.ece\/REPRESENTATIONS\/poster_100x141\/Dark%20Windows%20Teaserposter%20for%20skjerm%20-%20Kommer%20p%C3%A5%20kino"},{"url":"https:\/\/www.filmweb.no\/article1515565.ece\/REPRESENTATIONS\/poster_200x282\/Dark%20Windows%20Teaserposter%20for%20skjerm%20-%20Kommer%20p%C3%A5%20kino"},{"url":"https:\/\/www.filmweb.no\/article1515565.ece\/REPRESENTATIONS\/poster_300x424\/Dark%20Windows%20Teaserposter%20for%20skjerm%20-%20Kommer%20p%C3%A5%20kino"},{"url":"https:\/\/www.filmweb.no\/article1515565.ece\/REPRESENTATIONS\/poster_400x564\/Dark%20Windows%20Teaserposter%20for%20skjerm%20-%20Kommer%20p%C3%A5%20kino"},{"url":"https:\/\/www.filmweb.no\/article1515565.ece\/REPRESENTATIONS\/poster_600x848\/Dark%20Windows%20Teaserposter%20for%20skjerm%20-%20Kommer%20p%C3%A5%20kino"}]},"sanityImagePosterUrl":"https:\/\/cdn.sanity.io\/images\/j0wdmpyb\/production\/663a5411616625afa43f3ce558ca10a8f7454542-1240x1754.jpg?auto=format","shows":[{"firmName":"Sandnes Kino","showStart":"2024-02-08T21:00:00","screenName":"Sal 4 Sandnes","ticketSaleUrl":"https:\/\/www.odeonkino.no\/api\/v2\/redirect\/show\/Sys99-NO\/1ea3862b-09f4-4167-8c61-71937d13c2b7","theaterName":"Sandnes Kino","movieVersionId":"SFN20231704"},{"firmName":"Sandnes Kino","showStart":"2024-02-09T21:30:00","screenName":"Sal 4 Sandnes","ticketSaleUrl":"https:\/\/www.odeonkino.no\/api\/v2\/redirect\/show\/Sys99-NO\/747c64d8-73f3-4ec9-87ce-bc2c3559e7b5","theaterName":"Sandnes Kino","movieVersionId":"SFN20231704"}]},{"mainVersionId":"SFN20241717","title":"Demon Slayer: To the Hashira Training","genres":["Animasjon"],"lengthInMinutes":103,"rating":"12 \u00e5r","poster":null,"sanityImagePosterUrl":"https:\/\/cdn.sanity.io\/images\/j0wdmpyb\/production\/eb77fda496b91f55925997e349890f3595f16cc1-1240x1754.jpg?auto=format","shows":[{"firmName":"Sandnes Kino","showStart":"2024-02-23T18:30:00","screenName":"Sal 4 Sandnes","ticketSaleUrl":"https:\/\/www.odeonkino.no\/api\/v2\/redirect\/show\/Sys99-NO\/eaf3ffba-d576-44cd-a4c8-a2725220ad45","theaterName":"Sandnes Kino","movieVersionId":"SFN20241717"}]},{"mainVersionId":"FOP20230203","title":"Detektiv Edderkopp","genres":[],"lengthInMinutes":88,"rating":"6 \u00e5r","poster":{"versions":[{"url":"https:\/\/www.filmweb.no\/article1519208.ece\/REPRESENTATIONS\/poster_100x141\/Detektiv%20Edderkopp%20Plakat%20i%20A4-format"},{"url":"https:\/\/www.filmweb.no\/article1519208.ece\/REPRESENTATIONS\/poster_200x282\/Detektiv%20Edderkopp%20Plakat%20i%20A4-format"},{"url":"https:\/\/www.filmweb.no\/article1519208.ece\/REPRESENTATIONS\/poster_300x424\/Detektiv%20Edderkopp%20Plakat%20i%20A4-format"},{"url":"https:\/\/www.filmweb.no\/article1519208.ece\/REPRESENTATIONS\/poster_400x564\/Detektiv%20Edderkopp%20Plakat%20i%20A4-format"},{"url":"https:\/\/www.filmweb.no\/article1519208.ece\/REPRESENTATIONS\/poster_600x848\/Detektiv%20Edderkopp%20Plakat%20i%20A4-format"}]},"sanityImagePosterUrl":"https:\/\/cdn.sanity.io\/images\/j0wdmpyb\/production\/c43fb570454e60cae67a27381e6598b2b7718001-1500x2122.webp?auto=format","shows":[{"firmName":"Sandnes Kino","showStart":"2024-02-09T16:20:00","screenName":"Sal 5 Sandnes","ticketSaleUrl":"https:\/\/www.odeonkino.no\/api\/v2\/redirect\/show\/Sys99-NO\/c577903f-3da5-4984-95d1-58e2c36a5efd","theaterName":"Sandnes Kino","movieVersionId":"FOP20230203"},{"firmName":"Sandnes Kino","showStart":"2024-02-10T11:30:00","screenName":"Sal 7 - VIP","ticketSaleUrl":"https:\/\/www.odeonkino.no\/api\/v2\/redirect\/show\/Sys99-NO\/e45fe97b-5aa8-4cec-83ea-259eed9b7730","theaterName":"Sandnes Kino","movieVersionId":"FOP20230203"},{"firmName":"Sandnes Kino","showStart":"2024-02-10T12:45:00","screenName":"Sal 5 Sandnes","ticketSaleUrl":"https:\/\/www.odeonkino.no\/api\/v2\/redirect\/show\/Sys99-NO\/8aa6a7bf-db25-4090-af2b-b7597669a7da","theaterName":"Sandnes Kino","movieVersionId":"FOP20230203"},{"firmName":"Sandnes Kino","showStart":"2024-02-11T12:45:00","screenName":"Sal 5 Sandnes","ticketSaleUrl":"https:\/\/www.odeonkino.no\/api\/v2\/redirect\/show\/Sys99-NO\/bd535962-f22e-482b-a11a-db6d9f8a13de","theaterName":"Sandnes Kino","movieVersionId":"FOP20230203"},{"firmName":"Sandnes Kino","showStart":"2024-02-13T16:20:00","screenName":"Sal 3 Sandnes","ticketSaleUrl":"https:\/\/www.odeonkino.no\/api\/v2\/redirect\/show\/Sys99-NO\/f8b43838-5539-4ddb-a18a-59758645c8d1","theaterName":"Sandnes Kino","movieVersionId":"FOP20230203"}]},{"mainVersionId":"YME20230100","title":"Dream Scenario","genres":["Drama","Komedie","Sort komedie"],"lengthInMinutes":102,"rating":"15 \u00e5r","poster":{"versions":[{"url":"https:\/\/www.filmweb.no\/article1519955.ece\/REPRESENTATIONS\/poster_100x141\/Dream%20Scenario%20DreamScenario_Poster_70x100_NO.jpg"},{"url":"https:\/\/www.filmweb.no\/article1519955.ece\/REPRESENTATIONS\/poster_200x282\/Dream%20Scenario%20DreamScenario_Poster_70x100_NO.jpg"},{"url":"https:\/\/www.filmweb.no\/article1519955.ece\/REPRESENTATIONS\/poster_300x424\/Dream%20Scenario%20DreamScenario_Poster_70x100_NO.jpg"},{"url":"https:\/\/www.filmweb.no\/article1519955.ece\/REPRESENTATIONS\/poster_400x564\/Dream%20Scenario%20DreamScenario_Poster_70x100_NO.jpg"},{"url":"https:\/\/www.filmweb.no\/article1519955.ece\/REPRESENTATIONS\/poster_600x848\/Dream%20Scenario%20DreamScenario_Poster_70x100_NO.jpg"}]},"sanityImagePosterUrl":"https:\/\/cdn.sanity.io\/images\/j0wdmpyb\/production\/4a7a3f8aa1d1ca51bffebba1f02e42bda7558173-1080x1514.jpg?auto=format","shows":[{"firmName":"Sandnes Kino","showStart":"2024-02-08T12:30:00","screenName":"Sal 5 Sandnes","ticketSaleUrl":"https:\/\/www.odeonkino.no\/api\/v2\/redirect\/show\/Sys99-NO\/f1085206-187e-431b-a7a1-a42c5e0a33cd","theaterName":"Sandnes Kino","movieVersionId":"YME20230100"},{"firmName":"Sandnes Kino","showStart":"2024-02-09T21:00:00","screenName":"Sal 7 - VIP","ticketSaleUrl":"https:\/\/www.odeonkino.no\/api\/v2\/redirect\/show\/Sys99-NO\/fdb0e24e-4f3c-488f-8e52-3612c5e46f44","theaterName":"Sandnes Kino","movieVersionId":"YME20230100"},{"firmName":"Sandnes Kino","showStart":"2024-02-10T20:30:00","screenName":"Sal 7 - VIP","ticketSaleUrl":"https:\/\/www.odeonkino.no\/api\/v2\/redirect\/show\/Sys99-NO\/bc3ccd8e-2f58-403e-99cb-bf2569f16081","theaterName":"Sandnes Kino","movieVersionId":"YME20230100"},{"firmName":"Sandnes Kino","showStart":"2024-02-11T20:45:00","screenName":"Sal 7 - VIP","ticketSaleUrl":"https:\/\/www.odeonkino.no\/api\/v2\/redirect\/show\/Sys99-NO\/779ae0ab-20d2-48ea-942b-da1305647c00","theaterName":"Sandnes Kino","movieVersionId":"YME20230100"},{"firmName":"Sandnes Kino","showStart":"2024-02-13T20:30:00","screenName":"Sal 7 - VIP","ticketSaleUrl":"https:\/\/www.odeonkino.no\/api\/v2\/redirect\/show\/Sys99-NO\/b0ffe900-cb90-419a-a86f-06bd14bc506b","theaterName":"Sandnes Kino","movieVersionId":"YME20230100"}]},{"mainVersionId":"SFN20211456","title":"Dune: Part Two","genres":["Action","Drama","Eventyr","Sci-Fi"],"lengthInMinutes":166,"rating":"12 \u00e5r","poster":{"versions":[{"url":"https:\/\/www.filmweb.no\/article1512595.ece\/REPRESENTATIONS\/poster_100x141\/Dune:%20Part%20Two%20DP2%20teaserplakat"},{"url":"https:\/\/www.filmweb.no\/article1512595.ece\/REPRESENTATIONS\/poster_200x282\/Dune:%20Part%20Two%20DP2%20teaserplakat"},{"url":"https:\/\/www.filmweb.no\/article1512595.ece\/REPRESENTATIONS\/poster_300x424\/Dune:%20Part%20Two%20DP2%20teaserplakat"},{"url":"https:\/\/www.filmweb.no\/article1512595.ece\/REPRESENTATIONS\/poster_400x564\/Dune:%20Part%20Two%20DP2%20teaserplakat"},{"url":"https:\/\/www.filmweb.no\/article1512595.ece\/REPRESENTATIONS\/poster_600x848\/Dune:%20Part%20Two%20DP2%20teaserplakat"}]},"sanityImagePosterUrl":"https:\/\/cdn.sanity.io\/images\/j0wdmpyb\/production\/e83ec0bb540ed5cd76cb02d68845c6832ce59d7f-595x842.jpg?auto=format","shows":[{"firmName":"Sandnes Kino","showStart":"2024-02-28T11:00:00","screenName":"Sal 6 LUXE","ticketSaleUrl":"https:\/\/www.odeonkino.no\/api\/v2\/redirect\/show\/Sys99-NO\/692a5033-718a-46aa-86dd-4f49c65dead5","theaterName":"Sandnes Kino","movieVersionId":"WAB20240204"},{"firmName":"Sandnes Kino","showStart":"2024-02-28T13:00:00","screenName":"Sal 1 - isense by BATE","ticketSaleUrl":"https:\/\/www.odeonkino.no\/api\/v2\/redirect\/show\/Sys99-NO\/f25bfa7b-6a8d-4825-b468-535edf88ce12","theaterName":"Sandnes Kino","movieVersionId":"WAB20240204"},{"firmName":"Sandnes Kino","showStart":"2024-02-28T14:30:00","screenName":"Sal 6 LUXE","ticketSaleUrl":"https:\/\/www.odeonkino.no\/api\/v2\/redirect\/show\/Sys99-NO\/07d02936-898a-4908-82b7-1bfc6d4ed321","theaterName":"Sandnes Kino","movieVersionId":"WAB20240204"},{"firmName":"Sandnes Kino","showStart":"2024-02-28T17:00:00","screenName":"Sal 1 - isense by BATE","ticketSaleUrl":"https:\/\/www.odeonkino.no\/api\/v2\/redirect\/show\/Sys99-NO\/401d4e9d-3a71-4f4c-a5a6-617bd34222e4","theaterName":"Sandnes Kino","movieVersionId":"WAB20240204"},{"firmName":"Sandnes Kino","showStart":"2024-02-28T20:30:00","screenName":"Sal 1 - isense by BATE","ticketSaleUrl":"https:\/\/www.odeonkino.no\/api\/v2\/redirect\/show\/Sys99-NO\/a44b465e-e3da-468f-b489-97ca490483c2","theaterName":"Sandnes Kino","movieVersionId":"WAB20240204"},{"firmName":"Sandnes Kino","showStart":"2024-02-29T11:00:00","screenName":"Sal 6 LUXE","ticketSaleUrl":"https:\/\/www.odeonkino.no\/api\/v2\/redirect\/show\/Sys99-NO\/7a4b513d-8bff-4a29-8ed2-2508628826ef","theaterName":"Sandnes Kino","movieVersionId":"WAB20240204"},{"firmName":"Sandnes Kino","showStart":"2024-02-29T13:00:00","screenName":"Sal 1 - isense by BATE","ticketSaleUrl":"https:\/\/www.odeonkino.no\/api\/v2\/redirect\/show\/Sys99-NO\/1c60662b-e433-48b1-ae25-066982bbb7dc","theaterName":"Sandnes Kino","movieVersionId":"WAB20240204"},{"firmName":"Sandnes Kino","showStart":"2024-02-29T14:30:00","screenName":"Sal 6 LUXE","ticketSaleUrl":"https:\/\/www.odeonkino.no\/api\/v2\/redirect\/show\/Sys99-NO\/3363b325-c7a8-4478-8404-a81e15e3b9eb","theaterName":"Sandnes Kino","movieVersionId":"WAB20240204"},{"firmName":"Sandnes Kino","showStart":"2024-02-29T17:00:00","screenName":"Sal 1 - isense by BATE","ticketSaleUrl":"https:\/\/www.odeonkino.no\/api\/v2\/redirect\/show\/Sys99-NO\/66e30d2f-58ea-4f9a-8ed7-99cef0c94eae","theaterName":"Sandnes Kino","movieVersionId":"WAB20240204"},{"firmName":"Sandnes Kino","showStart":"2024-02-29T20:30:00","screenName":"Sal 1 - isense by BATE","ticketSaleUrl":"https:\/\/www.odeonkino.no\/api\/v2\/redirect\/show\/Sys99-NO\/3c59fbbf-55d0-4fe4-8e41-92bb70edcaf2","theaterName":"Sandnes Kino","movieVersionId":"WAB20240204"},{"firmName":"Sandnes Kino","showStart":"2024-03-01T11:00:00","screenName":"Sal 6 LUXE","ticketSaleUrl":"https:\/\/www.odeonkino.no\/api\/v2\/redirect\/show\/Sys99-NO\/0d86bb3d-69a2-4305-a9b1-13949ee26cf8","theaterName":"Sandnes Kino","movieVersionId":"WAB20240204"},{"firmName":"Sandnes Kino","showStart":"2024-03-01T14:00:00","screenName":"Sal 1 - isense by BATE","ticketSaleUrl":"https:\/\/www.odeonkino.no\/api\/v2\/redirect\/show\/Sys99-NO\/cfb4273e-d0b6-4be8-bf91-c59265404e25","theaterName":"Sandnes Kino","movieVersionId":"WAB20240204"},{"firmName":"Sandnes Kino","showStart":"2024-03-01T14:30:00","screenName":"Sal 6 LUXE","ticketSaleUrl":"https:\/\/www.odeonkino.no\/api\/v2\/redirect\/show\/Sys99-NO\/91a4aff0-0121-4edc-8d7f-97788eb9ae7f","theaterName":"Sandnes Kino","movieVersionId":"WAB20240204"},{"firmName":"Sandnes Kino","showStart":"2024-03-01T17:30:00","screenName":"Sal 1 - isense by BATE","ticketSaleUrl":"https:\/\/www.odeonkino.no\/api\/v2\/redirect\/show\/Sys99-NO\/e91d1c88-b969-484a-a403-e68efe94279d","theaterName":"Sandnes Kino","movieVersionId":"WAB20240204"},{"firmName":"Sandnes Kino","showStart":"2024-03-01T21:00:00","screenName":"Sal 1 - isense by BATE","ticketSaleUrl":"https:\/\/www.odeonkino.no\/api\/v2\/redirect\/show\/Sys99-NO\/b275e1d5-e85e-4b19-8be6-b7517b749e63","theaterName":"Sandnes Kino","movieVersionId":"WAB20240204"},{"firmName":"Sandnes Kino","showStart":"2024-03-02T11:00:00","screenName":"Sal 6 LUXE","ticketSaleUrl":"https:\/\/www.odeonkino.no\/api\/v2\/redirect\/show\/Sys99-NO\/367831d4-f6cf-4114-b79b-91b5c474cb4b","theaterName":"Sandnes Kino","movieVersionId":"WAB20240204"},{"firmName":"Sandnes Kino","showStart":"2024-03-02T13:30:00","screenName":"Sal 1 - isense by BATE","ticketSaleUrl":"https:\/\/www.odeonkino.no\/api\/v2\/redirect\/show\/Sys99-NO\/422c7365-4721-47f8-998b-e620be2e6b48","theaterName":"Sandnes Kino","movieVersionId":"WAB20240204"},{"firmName":"Sandnes Kino","showStart":"2024-03-02T14:30:00","screenName":"Sal 6 LUXE","ticketSaleUrl":"https:\/\/www.odeonkino.no\/api\/v2\/redirect\/show\/Sys99-NO\/49158ab6-71d1-484d-b752-c1f69c4b2d66","theaterName":"Sandnes Kino","movieVersionId":"WAB20240204"},{"firmName":"Sandnes Kino","showStart":"2024-03-02T17:30:00","screenName":"Sal 1 - isense by BATE","ticketSaleUrl":"https:\/\/www.odeonkino.no\/api\/v2\/redirect\/show\/Sys99-NO\/44ef149b-7ff8-41ae-8a7f-2bfa1d7277ee","theaterName":"Sandnes Kino","movieVersionId":"WAB20240204"},{"firmName":"Sandnes Kino","showStart":"2024-03-02T21:00:00","screenName":"Sal 1 - isense by BATE","ticketSaleUrl":"https:\/\/www.odeonkino.no\/api\/v2\/redirect\/show\/Sys99-NO\/0e5bc431-f477-4387-81e5-c414751eceb0","theaterName":"Sandnes Kino","movieVersionId":"WAB20240204"},{"firmName":"Sandnes Kino","showStart":"2024-03-03T12:15:00","screenName":"Sal 6 LUXE","ticketSaleUrl":"https:\/\/www.odeonkino.no\/api\/v2\/redirect\/show\/Sys99-NO\/5bd4e98e-9dab-4f6f-92ae-fd4439cc570c","theaterName":"Sandnes Kino","movieVersionId":"WAB20240204"},{"firmName":"Sandnes Kino","showStart":"2024-03-03T13:00:00","screenName":"Sal 1 - isense by BATE","ticketSaleUrl":"https:\/\/www.odeonkino.no\/api\/v2\/redirect\/show\/Sys99-NO\/77294c12-2d0a-4890-9016-ce4b70a10e11","theaterName":"Sandnes Kino","movieVersionId":"WAB20240204"},{"firmName":"Sandnes Kino","showStart":"2024-03-03T15:45:00","screenName":"Sal 6 LUXE","ticketSaleUrl":"https:\/\/www.odeonkino.no\/api\/v2\/redirect\/show\/Sys99-NO\/2a6c70cc-2884-4a91-b107-f70be722b9d3","theaterName":"Sandnes Kino","movieVersionId":"WAB20240204"},{"firmName":"Sandnes Kino","showStart":"2024-03-03T17:00:00","screenName":"Sal 1 - isense by BATE","ticketSaleUrl":"https:\/\/www.odeonkino.no\/api\/v2\/redirect\/show\/Sys99-NO\/bd57298a-283e-409d-8dc7-325de3fcce9f","theaterName":"Sandnes Kino","movieVersionId":"WAB20240204"},{"firmName":"Sandnes Kino","showStart":"2024-03-03T20:30:00","screenName":"Sal 1 - isense by BATE","ticketSaleUrl":"https:\/\/www.odeonkino.no\/api\/v2\/redirect\/show\/Sys99-NO\/4214d3b0-b5e7-4371-9195-905a4f17e07b","theaterName":"Sandnes Kino","movieVersionId":"WAB20240204"}]},{"mainVersionId":"WAB20240208","title":"Dune-maraton","genres":["Action","Drama","Eventyr","Sci-Fi"],"lengthInMinutes":0,"rating":"12 \u00e5r","poster":null,"sanityImagePosterUrl":"https:\/\/cdn.sanity.io\/images\/j0wdmpyb\/production\/bea29817dc83d0960eb015674176e74ea95183d1-595x841.jpg?auto=format","shows":[{"firmName":"Sandnes Kino","showStart":"2024-02-27T17:30:00","screenName":"Sal 1 - isense by BATE","ticketSaleUrl":"https:\/\/www.odeonkino.no\/api\/v2\/redirect\/show\/Sys99-NO\/0164cb51-b963-4c96-a80a-f4a47c7eed36","theaterName":"Sandnes Kino","movieVersionId":"WAB20240209"}]},{"mainVersionId":"UIP20221364","title":"Ender p\u00e5 eventyr","genres":["Animasjon","Barnefilm"],"lengthInMinutes":91,"rating":"6 \u00e5r","poster":{"versions":[{"url":"https:\/\/www.filmweb.no\/article1519322.ece\/REPRESENTATIONS\/poster_100x141\/Ender%20p%C3%A5%20eventyr%20A4"},{"url":"https:\/\/www.filmweb.no\/article1519322.ece\/REPRESENTATIONS\/poster_200x282\/Ender%20p%C3%A5%20eventyr%20A4"},{"url":"https:\/\/www.filmweb.no\/article1519322.ece\/REPRESENTATIONS\/poster_300x424\/Ender%20p%C3%A5%20eventyr%20A4"},{"url":"https:\/\/www.filmweb.no\/article1519322.ece\/REPRESENTATIONS\/poster_400x564\/Ender%20p%C3%A5%20eventyr%20A4"},{"url":"https:\/\/www.filmweb.no\/article1519322.ece\/REPRESENTATIONS\/poster_600x848\/Ender%20p%C3%A5%20eventyr%20A4"}]},"sanityImagePosterUrl":"https:\/\/cdn.sanity.io\/images\/j0wdmpyb\/production\/43ef9ff6da556b9b8417ed94c0a846bb29741b12-1500x2122.webp?auto=format","shows":[{"firmName":"Sandnes Kino","showStart":"2024-02-10T11:30:00","screenName":"Sal 3 Sandnes","ticketSaleUrl":"https:\/\/www.odeonkino.no\/api\/v2\/redirect\/show\/Sys99-NO\/1ec26bd4-3de6-410a-9ae4-ef6a33da5c2e","theaterName":"Sandnes Kino","movieVersionId":"UIP20231608"},{"firmName":"Sandnes Kino","showStart":"2024-02-10T16:00:00","screenName":"Sal 3 Sandnes","ticketSaleUrl":"https:\/\/www.odeonkino.no\/api\/v2\/redirect\/show\/Sys99-NO\/d72409d4-27dd-43a5-8905-008daab07daf","theaterName":"Sandnes Kino","movieVersionId":"UIP20231608"},{"firmName":"Sandnes Kino","showStart":"2024-02-11T13:00:00","screenName":"Sal 3 Sandnes","ticketSaleUrl":"https:\/\/www.odeonkino.no\/api\/v2\/redirect\/show\/Sys99-NO\/e75e8d70-37b9-4bd3-8b09-82033edfae44","theaterName":"Sandnes Kino","movieVersionId":"UIP20221364"}]},{"mainVersionId":"UAV20237720","title":"Fest med Smurfene","genres":[],"lengthInMinutes":0,"rating":"","poster":null,"sanityImagePosterUrl":"","shows":[{"firmName":"Sandnes Kino","showStart":"2024-02-10T11:00:00","screenName":"Sal 5 Sandnes","ticketSaleUrl":"https:\/\/www.odeonkino.no\/api\/v2\/redirect\/show\/Sys99-NO\/60188d1c-0701-479d-8e15-d2496ab4f7c7","theaterName":"Sandnes Kino","movieVersionId":"UAV20237720"}]},{"mainVersionId":"NOR20210546","title":"H\u00e5ndtering av ud\u00f8de","genres":["Drama"],"lengthInMinutes":97,"rating":"15 \u00e5r","poster":{"versions":[{"url":"https:\/\/www.filmweb.no\/article1519687.ece\/REPRESENTATIONS\/poster_100x141\/H%C3%A5ndtering%20av%20ud%C3%B8de%20A4_skjerm.png"},{"url":"https:\/\/www.filmweb.no\/article1519687.ece\/REPRESENTATIONS\/poster_200x282\/H%C3%A5ndtering%20av%20ud%C3%B8de%20A4_skjerm.png"},{"url":"https:\/\/www.filmweb.no\/article1519687.ece\/REPRESENTATIONS\/poster_300x424\/H%C3%A5ndtering%20av%20ud%C3%B8de%20A4_skjerm.png"},{"url":"https:\/\/www.filmweb.no\/article1519687.ece\/REPRESENTATIONS\/poster_400x564\/H%C3%A5ndtering%20av%20ud%C3%B8de%20A4_skjerm.png"},{"url":"https:\/\/www.filmweb.no\/article1519687.ece\/REPRESENTATIONS\/poster_600x848\/H%C3%A5ndtering%20av%20ud%C3%B8de%20A4_skjerm.png"}]},"sanityImagePosterUrl":"https:\/\/cdn.sanity.io\/images\/j0wdmpyb\/production\/c7c8858e89961e0f8d6761328f28918e01fdc33b-1500x2122.webp?auto=format","shows":[{"firmName":"Sandnes Kino","showStart":"2024-02-09T19:00:00","screenName":"Sal 4 Sandnes","ticketSaleUrl":"https:\/\/www.odeonkino.no\/api\/v2\/redirect\/show\/Sys99-NO\/9f37506d-949b-49dd-8b57-22f1d7e02cc3","theaterName":"Sandnes Kino","movieVersionId":"NOR20210546"},{"firmName":"Sandnes Kino","showStart":"2024-02-10T18:30:00","screenName":"Sal 4 Sandnes","ticketSaleUrl":"https:\/\/www.odeonkino.no\/api\/v2\/redirect\/show\/Sys99-NO\/88bf6563-5cb5-4109-b0fd-190f250dbca1","theaterName":"Sandnes Kino","movieVersionId":"NOR20210546"},{"firmName":"Sandnes Kino","showStart":"2024-02-11T18:15:00","screenName":"Sal 7 - VIP","ticketSaleUrl":"https:\/\/www.odeonkino.no\/api\/v2\/redirect\/show\/Sys99-NO\/1ce2f3f8-79b7-4cb0-8cdf-ad5cb1ca0f81","theaterName":"Sandnes Kino","movieVersionId":"NOR20210546"},{"firmName":"Sandnes Kino","showStart":"2024-02-11T20:30:00","screenName":"Sal 4 Sandnes","ticketSaleUrl":"https:\/\/www.odeonkino.no\/api\/v2\/redirect\/show\/Sys99-NO\/cb45e1b3-837b-4f13-b358-ff538b4de4fd","theaterName":"Sandnes Kino","movieVersionId":"NOR20210546"},{"firmName":"Sandnes Kino","showStart":"2024-02-13T19:30:00","screenName":"Sal 4 Sandnes","ticketSaleUrl":"https:\/\/www.odeonkino.no\/api\/v2\/redirect\/show\/Sys99-NO\/73abf754-7d30-4b95-8138-61713955fdd6","theaterName":"Sandnes Kino","movieVersionId":"NOR20210546"},{"firmName":"Sandnes Kino","showStart":"2024-02-15T12:30:00","screenName":"Sal 5 Sandnes","ticketSaleUrl":"https:\/\/www.odeonkino.no\/api\/v2\/redirect\/show\/Sys99-NO\/cc5ff1ba-5a7a-414f-89cd-0c0e1f52a6ea","theaterName":"Sandnes Kino","movieVersionId":"NOR20210546"}]},{"mainVersionId":"AWE20230433","title":"Jungelgjengen p\u00e5 Verdensturn\u00e9","genres":["Animasjon","Barnefilm","Familiefilm"],"lengthInMinutes":88,"rating":"Tillatt for alle","poster":{"versions":[{"url":"https:\/\/www.filmweb.no\/incoming\/article1516499.ece\/REPRESENTATIONS\/poster_100x141\/Junglebanden"},{"url":"https:\/\/www.filmweb.no\/incoming\/article1516499.ece\/REPRESENTATIONS\/poster_200x282\/Junglebanden"},{"url":"https:\/\/www.filmweb.no\/incoming\/article1516499.ece\/REPRESENTATIONS\/poster_300x424\/Junglebanden"},{"url":"https:\/\/www.filmweb.no\/incoming\/article1516499.ece\/REPRESENTATIONS\/poster_400x564\/Junglebanden"},{"url":"https:\/\/www.filmweb.no\/incoming\/article1516499.ece\/REPRESENTATIONS\/poster_600x848\/Junglebanden"}]},"sanityImagePosterUrl":"https:\/\/cdn.sanity.io\/images\/j0wdmpyb\/production\/bda2ffae69e9a8a2b80a6bde4b298759821f73f4-1500x2143.webp?auto=format","shows":[{"firmName":"Sandnes Kino","showStart":"2024-02-08T16:15:00","screenName":"Sal 4 Sandnes","ticketSaleUrl":"https:\/\/www.odeonkino.no\/api\/v2\/redirect\/show\/Sys99-NO\/58bd5d82-aab9-435a-83fb-a6e442c07fdb","theaterName":"Sandnes Kino","movieVersionId":"AWE20230433"},{"firmName":"Sandnes Kino","showStart":"2024-02-10T10:50:00","screenName":"Sal 4 Sandnes","ticketSaleUrl":"https:\/\/www.odeonkino.no\/api\/v2\/redirect\/show\/Sys99-NO\/38654783-577c-4da4-a679-836771f08870","theaterName":"Sandnes Kino","movieVersionId":"AWE20230433"},{"firmName":"Sandnes Kino","showStart":"2024-02-10T13:30:00","screenName":"Sal 7 - VIP","ticketSaleUrl":"https:\/\/www.odeonkino.no\/api\/v2\/redirect\/show\/Sys99-NO\/de86cdc4-5840-4006-aea6-89bd5251cdbf","theaterName":"Sandnes Kino","movieVersionId":"AWE20230433"},{"firmName":"Sandnes Kino","showStart":"2024-02-11T13:30:00","screenName":"Sal 4 Sandnes","ticketSaleUrl":"https:\/\/www.odeonkino.no\/api\/v2\/redirect\/show\/Sys99-NO\/734fc37c-6947-4929-ace5-c9c1ded6870b","theaterName":"Sandnes Kino","movieVersionId":"AWE20230433"},{"firmName":"Sandnes Kino","showStart":"2024-02-12T16:20:00","screenName":"Sal 1 - isense by BATE","ticketSaleUrl":"https:\/\/www.odeonkino.no\/api\/v2\/redirect\/show\/Sys99-NO\/0f3bebeb-0d73-42ce-bdd4-e6fa498a86ce","theaterName":"Sandnes Kino","movieVersionId":"AWE20230433"},{"firmName":"Sandnes Kino","showStart":"2024-02-13T16:20:00","screenName":"Sal 1 - isense by BATE","ticketSaleUrl":"https:\/\/www.odeonkino.no\/api\/v2\/redirect\/show\/Sys99-NO\/8c844b0f-14e1-418d-9105-f4d69e82ac5d","theaterName":"Sandnes Kino","movieVersionId":"AWE20230433"}]},{"mainVersionId":"NOR20210544","title":"Konvoi","genres":["Krigsfilm","Spenning"],"lengthInMinutes":108,"rating":"12 \u00e5r","poster":{"versions":[{"url":"https:\/\/www.filmweb.no\/article1518686.ece\/REPRESENTATIONS\/poster_100x141\/Konvoi%20Konvoi_A4_skjerm.jpg"},{"url":"https:\/\/www.filmweb.no\/article1518686.ece\/REPRESENTATIONS\/poster_200x282\/Konvoi%20Konvoi_A4_skjerm.jpg"},{"url":"https:\/\/www.filmweb.no\/article1518686.ece\/REPRESENTATIONS\/poster_300x424\/Konvoi%20Konvoi_A4_skjerm.jpg"},{"url":"https:\/\/www.filmweb.no\/article1518686.ece\/REPRESENTATIONS\/poster_400x564\/Konvoi%20Konvoi_A4_skjerm.jpg"},{"url":"https:\/\/www.filmweb.no\/article1518686.ece\/REPRESENTATIONS\/poster_600x848\/Konvoi%20Konvoi_A4_skjerm.jpg"}]},"sanityImagePosterUrl":"https:\/\/cdn.sanity.io\/images\/j0wdmpyb\/production\/cf7160795a224c0550adc967c9fc346c14e3f411-1240x1754.jpg?auto=format","shows":[{"firmName":"Sandnes Kino","showStart":"2024-02-08T17:30:00","screenName":"Sal 3 Sandnes","ticketSaleUrl":"https:\/\/www.odeonkino.no\/api\/v2\/redirect\/show\/Sys99-NO\/f7b1f67a-34a3-4a67-9ece-05ef720d031f","theaterName":"Sandnes Kino","movieVersionId":"NOR20230689"},{"firmName":"Sandnes Kino","showStart":"2024-02-09T20:30:00","screenName":"Sal 3 Sandnes","ticketSaleUrl":"https:\/\/www.odeonkino.no\/api\/v2\/redirect\/show\/Sys99-NO\/e12bebcf-41e7-4e89-a459-78ca86f763a7","theaterName":"Sandnes Kino","movieVersionId":"NOR20230689"},{"firmName":"Sandnes Kino","showStart":"2024-02-10T21:00:00","screenName":"Sal 4 Sandnes","ticketSaleUrl":"https:\/\/www.odeonkino.no\/api\/v2\/redirect\/show\/Sys99-NO\/8689051d-2ee1-4903-9848-d6946a322b0c","theaterName":"Sandnes Kino","movieVersionId":"NOR20210544"},{"firmName":"Sandnes Kino","showStart":"2024-02-11T15:30:00","screenName":"Sal 7 - VIP","ticketSaleUrl":"https:\/\/www.odeonkino.no\/api\/v2\/redirect\/show\/Sys99-NO\/932de642-0d79-4bbe-9660-46a125ec7299","theaterName":"Sandnes Kino","movieVersionId":"NOR20210544"},{"firmName":"Sandnes Kino","showStart":"2024-02-13T18:00:00","screenName":"Sal 7 - VIP","ticketSaleUrl":"https:\/\/www.odeonkino.no\/api\/v2\/redirect\/show\/Sys99-NO\/bd563eda-61e5-46d2-8cf3-4249ea21fd9c","theaterName":"Sandnes Kino","movieVersionId":"NOR20210544"}]},{"mainVersionId":"SFN20231693","title":"Lassie - P\u00e5 nye eventyr","genres":["Familiefilm"],"lengthInMinutes":92,"rating":"6 \u00e5r","poster":{"versions":[{"url":"https:\/\/www.filmweb.no\/article1518026.ece\/REPRESENTATIONS\/poster_100x141\/Lassie%20-%20P%C3%A5%20nye%20eventyr!%20Lassie_A4_skjerm"},{"url":"https:\/\/www.filmweb.no\/article1518026.ece\/REPRESENTATIONS\/poster_200x282\/Lassie%20-%20P%C3%A5%20nye%20eventyr!%20Lassie_A4_skjerm"},{"url":"https:\/\/www.filmweb.no\/article1518026.ece\/REPRESENTATIONS\/poster_300x424\/Lassie%20-%20P%C3%A5%20nye%20eventyr!%20Lassie_A4_skjerm"},{"url":"https:\/\/www.filmweb.no\/article1518026.ece\/REPRESENTATIONS\/poster_400x564\/Lassie%20-%20P%C3%A5%20nye%20eventyr!%20Lassie_A4_skjerm"},{"url":"https:\/\/www.filmweb.no\/article1518026.ece\/REPRESENTATIONS\/poster_600x848\/Lassie%20-%20P%C3%A5%20nye%20eventyr!%20Lassie_A4_skjerm"}]},"sanityImagePosterUrl":"https:\/\/cdn.sanity.io\/images\/j0wdmpyb\/production\/542a7144bfbbfab2291f531aeb2eb2b99bff0f30-1000x1415.webp?auto=format","shows":[{"firmName":"Sandnes Kino","showStart":"2024-02-10T13:45:00","screenName":"Sal 3 Sandnes","ticketSaleUrl":"https:\/\/www.odeonkino.no\/api\/v2\/redirect\/show\/Sys99-NO\/8b4928fc-2072-48ea-8277-b2c2327c88e4","theaterName":"Sandnes Kino","movieVersionId":"SFN20231693"},{"firmName":"Sandnes Kino","showStart":"2024-02-11T15:45:00","screenName":"Sal 4 Sandnes","ticketSaleUrl":"https:\/\/www.odeonkino.no\/api\/v2\/redirect\/show\/Sys99-NO\/8d7fea97-1b73-416c-a1b6-de06d35c9a7f","theaterName":"Sandnes Kino","movieVersionId":"SFN20231693"},{"firmName":"Sandnes Kino","showStart":"2024-02-16T17:00:00","screenName":"Sal 7 - VIP","ticketSaleUrl":"https:\/\/www.odeonkino.no\/api\/v2\/redirect\/show\/Sys99-NO\/fd6cc29d-6695-42f8-b0f7-276d73d2deaf","theaterName":"Sandnes Kino","movieVersionId":"SFN20231693"}]},{"mainVersionId":"SFN20221537","title":"Madame Web","genres":[],"lengthInMinutes":116,"rating":"12 \u00e5r","poster":{"versions":[{"url":"https:\/\/www.filmweb.no\/article1519935.ece\/REPRESENTATIONS\/poster_100x141\/Madame%20Web%20A4%20skjerm"},{"url":"https:\/\/www.filmweb.no\/article1519935.ece\/REPRESENTATIONS\/poster_200x282\/Madame%20Web%20A4%20skjerm"},{"url":"https:\/\/www.filmweb.no\/article1519935.ece\/REPRESENTATIONS\/poster_300x424\/Madame%20Web%20A4%20skjerm"},{"url":"https:\/\/www.filmweb.no\/article1519935.ece\/REPRESENTATIONS\/poster_400x564\/Madame%20Web%20A4%20skjerm"},{"url":"https:\/\/www.filmweb.no\/article1519935.ece\/REPRESENTATIONS\/poster_600x848\/Madame%20Web%20A4%20skjerm"}]},"sanityImagePosterUrl":"https:\/\/cdn.sanity.io\/images\/j0wdmpyb\/production\/58bd873f5820cd87398e57786cd398122ee8d5c0-1240x1754.jpg?auto=format","shows":[{"firmName":"Sandnes Kino","showStart":"2024-02-14T18:00:00","screenName":"Sal 1 - isense by BATE","ticketSaleUrl":"https:\/\/www.odeonkino.no\/api\/v2\/redirect\/show\/Sys99-NO\/a12cf4f1-9b32-4e6e-98ed-7f02509a16a6","theaterName":"Sandnes Kino","movieVersionId":"SFN20241723"},{"firmName":"Sandnes Kino","showStart":"2024-02-14T20:45:00","screenName":"Sal 1 - isense by BATE","ticketSaleUrl":"https:\/\/www.odeonkino.no\/api\/v2\/redirect\/show\/Sys99-NO\/07b6f52b-de47-4610-9e0a-bd2dd5efb6c6","theaterName":"Sandnes Kino","movieVersionId":"SFN20241723"},{"firmName":"Sandnes Kino","showStart":"2024-02-15T12:15:00","screenName":"Sal 7 - VIP","ticketSaleUrl":"https:\/\/www.odeonkino.no\/api\/v2\/redirect\/show\/Sys99-NO\/2d48234a-0f78-446e-9396-320a90264fd2","theaterName":"Sandnes Kino","movieVersionId":"SFN20221537"},{"firmName":"Sandnes Kino","showStart":"2024-02-15T17:30:00","screenName":"Sal 1 - isense by BATE","ticketSaleUrl":"https:\/\/www.odeonkino.no\/api\/v2\/redirect\/show\/Sys99-NO\/82398af5-4b35-4f4b-afc6-88f1950989c1","theaterName":"Sandnes Kino","movieVersionId":"SFN20241723"},{"firmName":"Sandnes Kino","showStart":"2024-02-15T20:15:00","screenName":"Sal 1 - isense by BATE","ticketSaleUrl":"https:\/\/www.odeonkino.no\/api\/v2\/redirect\/show\/Sys99-NO\/3b084a2b-9675-44e1-b770-13449e228823","theaterName":"Sandnes Kino","movieVersionId":"SFN20241723"}]},{"mainVersionId":"UIP20231606","title":"Mean Girls","genres":["Komedie","Musikal"],"lengthInMinutes":112,"rating":"9 \u00e5r","poster":{"versions":[{"url":"https:\/\/www.filmweb.no\/article1519058.ece\/REPRESENTATIONS\/poster_100x141\/Mean%20Girls%20A4"},{"url":"https:\/\/www.filmweb.no\/article1519058.ece\/REPRESENTATIONS\/poster_200x282\/Mean%20Girls%20A4"},{"url":"https:\/\/www.filmweb.no\/article1519058.ece\/REPRESENTATIONS\/poster_300x424\/Mean%20Girls%20A4"},{"url":"https:\/\/www.filmweb.no\/article1519058.ece\/REPRESENTATIONS\/poster_400x564\/Mean%20Girls%20A4"},{"url":"https:\/\/www.filmweb.no\/article1519058.ece\/REPRESENTATIONS\/poster_600x848\/Mean%20Girls%20A4"}]},"sanityImagePosterUrl":"https:\/\/cdn.sanity.io\/images\/j0wdmpyb\/production\/e8de9b00d2ac96222d43717c96db4ac6ff46b779-1500x2122.webp?auto=format","shows":[{"firmName":"Sandnes Kino","showStart":"2024-02-08T18:30:00","screenName":"Sal 5 Sandnes","ticketSaleUrl":"https:\/\/www.odeonkino.no\/api\/v2\/redirect\/show\/Sys99-NO\/3622476a-7a81-4cc4-9e5c-adcc5befc0a1","theaterName":"Sandnes Kino","movieVersionId":"UIP20231606"},{"firmName":"Sandnes Kino","showStart":"2024-02-09T16:30:00","screenName":"Sal 4 Sandnes","ticketSaleUrl":"https:\/\/www.odeonkino.no\/api\/v2\/redirect\/show\/Sys99-NO\/926c8832-a794-4a53-9ce9-b1dab46b07ae","theaterName":"Sandnes Kino","movieVersionId":"UIP20231606"},{"firmName":"Sandnes Kino","showStart":"2024-02-10T15:30:00","screenName":"Sal 4 Sandnes","ticketSaleUrl":"https:\/\/www.odeonkino.no\/api\/v2\/redirect\/show\/Sys99-NO\/8896d50c-6f25-46b7-a26f-a7afacd139c4","theaterName":"Sandnes Kino","movieVersionId":"UIP20231606"},{"firmName":"Sandnes Kino","showStart":"2024-02-11T18:00:00","screenName":"Sal 4 Sandnes","ticketSaleUrl":"https:\/\/www.odeonkino.no\/api\/v2\/redirect\/show\/Sys99-NO\/246fb7bb-966f-4e5c-acc8-823dfe081ac8","theaterName":"Sandnes Kino","movieVersionId":"UIP20231606"}]},{"mainVersionId":"MER20230084","title":"Mirakelet i Gullsp\u00e5ng","genres":["Dokumentar"],"lengthInMinutes":107,"rating":"12 \u00e5r","poster":{"versions":[{"url":"https:\/\/www.filmweb.no\/article1519662.ece\/REPRESENTATIONS\/poster_100x141\/Mirakelet%20i%20Gullsp%C3%A5ng%20MIRAKELET%20I%20GULLSP%C3%85NG%20-%20A4.jpg"},{"url":"https:\/\/www.filmweb.no\/article1519662.ece\/REPRESENTATIONS\/poster_200x282\/Mirakelet%20i%20Gullsp%C3%A5ng%20MIRAKELET%20I%20GULLSP%C3%85NG%20-%20A4.jpg"},{"url":"https:\/\/www.filmweb.no\/article1519662.ece\/REPRESENTATIONS\/poster_300x424\/Mirakelet%20i%20Gullsp%C3%A5ng%20MIRAKELET%20I%20GULLSP%C3%85NG%20-%20A4.jpg"},{"url":"https:\/\/www.filmweb.no\/article1519662.ece\/REPRESENTATIONS\/poster_400x564\/Mirakelet%20i%20Gullsp%C3%A5ng%20MIRAKELET%20I%20GULLSP%C3%85NG%20-%20A4.jpg"},{"url":"https:\/\/www.filmweb.no\/article1519662.ece\/REPRESENTATIONS\/poster_600x848\/Mirakelet%20i%20Gullsp%C3%A5ng%20MIRAKELET%20I%20GULLSP%C3%85NG%20-%20A4.jpg"}]},"sanityImagePosterUrl":"https:\/\/cdn.sanity.io\/images\/j0wdmpyb\/production\/a7a044131612124688690a8453fe25c17680a1ee-1500x2143.webp?auto=format","shows":[{"firmName":"Sandnes Kino","showStart":"2024-02-08T12:40:00","screenName":"Sal 3 Sandnes","ticketSaleUrl":"https:\/\/www.odeonkino.no\/api\/v2\/redirect\/show\/Sys99-NO\/f93d5cd3-540a-4496-a29e-30d67d27b009","theaterName":"Sandnes Kino","movieVersionId":"MER20230084"},{"firmName":"Sandnes Kino","showStart":"2024-02-08T18:00:00","screenName":"Sal 6 LUXE","ticketSaleUrl":"https:\/\/www.odeonkino.no\/api\/v2\/redirect\/show\/Sys99-NO\/d2ce4b67-bb21-4821-9347-538490004bbf","theaterName":"Sandnes Kino","movieVersionId":"MER20230084"},{"firmName":"Sandnes Kino","showStart":"2024-02-09T18:00:00","screenName":"Sal 6 LUXE","ticketSaleUrl":"https:\/\/www.odeonkino.no\/api\/v2\/redirect\/show\/Sys99-NO\/f4ffd687-b823-41f7-80e9-d74802bf0780","theaterName":"Sandnes Kino","movieVersionId":"MER20230084"},{"firmName":"Sandnes Kino","showStart":"2024-02-10T18:15:00","screenName":"Sal 6 LUXE","ticketSaleUrl":"https:\/\/www.odeonkino.no\/api\/v2\/redirect\/show\/Sys99-NO\/1ad9a8ff-7cd7-4a33-a5a2-5cc218ed351f","theaterName":"Sandnes Kino","movieVersionId":"MER20230084"},{"firmName":"Sandnes Kino","showStart":"2024-02-11T17:30:00","screenName":"Sal 6 LUXE","ticketSaleUrl":"https:\/\/www.odeonkino.no\/api\/v2\/redirect\/show\/Sys99-NO\/bbd18c48-8f6d-4d26-9e2c-555cddea6c58","theaterName":"Sandnes Kino","movieVersionId":"MER20230084"},{"firmName":"Sandnes Kino","showStart":"2024-02-12T17:30:00","screenName":"Sal 6 LUXE","ticketSaleUrl":"https:\/\/www.odeonkino.no\/api\/v2\/redirect\/show\/Sys99-NO\/25b85aea-6829-4419-ba57-8ce3b55627a4","theaterName":"Sandnes Kino","movieVersionId":"MER20230084"},{"firmName":"Sandnes Kino","showStart":"2024-02-13T17:30:00","screenName":"Sal 6 LUXE","ticketSaleUrl":"https:\/\/www.odeonkino.no\/api\/v2\/redirect\/show\/Sys99-NO\/ade4f79a-8530-4640-82de-b1e5caacef3f","theaterName":"Sandnes Kino","movieVersionId":"MER20230084"}]},{"mainVersionId":"UIP20211337","title":"Oppenheimer","genres":["Drama"],"lengthInMinutes":180,"rating":"12 \u00e5r","poster":{"versions":[{"url":"https:\/\/www.filmweb.no\/incoming\/article1515287.ece\/REPRESENTATIONS\/poster_100x141\/a4_ny.jpg"},{"url":"https:\/\/www.filmweb.no\/incoming\/article1515287.ece\/REPRESENTATIONS\/poster_200x282\/a4_ny.jpg"},{"url":"https:\/\/www.filmweb.no\/incoming\/article1515287.ece\/REPRESENTATIONS\/poster_300x424\/a4_ny.jpg"},{"url":"https:\/\/www.filmweb.no\/incoming\/article1515287.ece\/REPRESENTATIONS\/poster_400x564\/a4_ny.jpg"},{"url":"https:\/\/www.filmweb.no\/incoming\/article1515287.ece\/REPRESENTATIONS\/poster_600x848\/a4_ny.jpg"}]},"sanityImagePosterUrl":"https:\/\/cdn.sanity.io\/images\/j0wdmpyb\/production\/506b68740383318602404ff27d5efc4c35158081-1000x1415.webp?auto=format","shows":[{"firmName":"Sandnes Kino","showStart":"2024-02-08T12:15:00","screenName":"Sal 7 - VIP","ticketSaleUrl":"https:\/\/www.odeonkino.no\/api\/v2\/redirect\/show\/Sys99-NO\/8c121cf9-f637-4fe7-810c-2cc1d05e49e3","theaterName":"Sandnes Kino","movieVersionId":"UIP20211337"}]},{"mainVersionId":"ART20230574","title":"Perfect Days","genres":["Drama"],"lengthInMinutes":124,"rating":"Tillatt for alle","poster":{"versions":[{"url":"https:\/\/www.filmweb.no\/article1519870.ece\/REPRESENTATIONS\/poster_100x141\/Perfect%20Days%20Perfect%20Days%20-%20norsk%20plakat"},{"url":"https:\/\/www.filmweb.no\/article1519870.ece\/REPRESENTATIONS\/poster_200x282\/Perfect%20Days%20Perfect%20Days%20-%20norsk%20plakat"},{"url":"https:\/\/www.filmweb.no\/article1519870.ece\/REPRESENTATIONS\/poster_300x424\/Perfect%20Days%20Perfect%20Days%20-%20norsk%20plakat"},{"url":"https:\/\/www.filmweb.no\/article1519870.ece\/REPRESENTATIONS\/poster_400x564\/Perfect%20Days%20Perfect%20Days%20-%20norsk%20plakat"},{"url":"https:\/\/www.filmweb.no\/article1519870.ece\/REPRESENTATIONS\/poster_600x848\/Perfect%20Days%20Perfect%20Days%20-%20norsk%20plakat"}]},"sanityImagePosterUrl":"https:\/\/cdn.sanity.io\/images\/j0wdmpyb\/production\/92617266d6fbbafbada457a2da5761cb45000cea-1500x2143.webp?auto=format","shows":[{"firmName":"Sandnes Kino","showStart":"2024-02-08T12:30:00","screenName":"Sal 6 LUXE","ticketSaleUrl":"https:\/\/www.odeonkino.no\/api\/v2\/redirect\/show\/Sys99-NO\/6cabc11b-9917-4cad-bd3c-6db5405e57dc","theaterName":"Sandnes Kino","movieVersionId":"ART20230574"}]},{"mainVersionId":"BVI20200539","title":"Poor Things","genres":["Coming of age","Drama","Eksperimentell","Komedie"],"lengthInMinutes":141,"rating":"15 \u00e5r","poster":{"versions":[{"url":"https:\/\/www.filmweb.no\/article1516831.ece\/REPRESENTATIONS\/poster_100x141\/Poor%20Things%20Payoff"},{"url":"https:\/\/www.filmweb.no\/article1516831.ece\/REPRESENTATIONS\/poster_200x282\/Poor%20Things%20Payoff"},{"url":"https:\/\/www.filmweb.no\/article1516831.ece\/REPRESENTATIONS\/poster_300x424\/Poor%20Things%20Payoff"},{"url":"https:\/\/www.filmweb.no\/article1516831.ece\/REPRESENTATIONS\/poster_400x564\/Poor%20Things%20Payoff"},{"url":"https:\/\/www.filmweb.no\/article1516831.ece\/REPRESENTATIONS\/poster_600x848\/Poor%20Things%20Payoff"}]},"sanityImagePosterUrl":"https:\/\/cdn.sanity.io\/images\/j0wdmpyb\/production\/cd1cf83aee4fcd9d51f2388aa9e14fd58bc5ec65-1500x2143.webp?auto=format","shows":[{"firmName":"Sandnes Kino","showStart":"2024-02-08T12:45:00","screenName":"Sal 4 Sandnes","ticketSaleUrl":"https:\/\/www.odeonkino.no\/api\/v2\/redirect\/show\/Sys99-NO\/d714a5c5-22aa-4380-ad39-fac81ab6fec6","theaterName":"Sandnes Kino","movieVersionId":"BVI20200539"},{"firmName":"Sandnes Kino","showStart":"2024-02-08T20:30:00","screenName":"Sal 6 LUXE","ticketSaleUrl":"https:\/\/www.odeonkino.no\/api\/v2\/redirect\/show\/Sys99-NO\/9366ecda-6659-4bd4-aa6e-744fd8037ae5","theaterName":"Sandnes Kino","movieVersionId":"BVI20230765"},{"firmName":"Sandnes Kino","showStart":"2024-02-09T20:30:00","screenName":"Sal 6 LUXE","ticketSaleUrl":"https:\/\/www.odeonkino.no\/api\/v2\/redirect\/show\/Sys99-NO\/89058bea-c428-44cb-9f78-4ad6f8b35c5e","theaterName":"Sandnes Kino","movieVersionId":"BVI20230765"},{"firmName":"Sandnes Kino","showStart":"2024-02-10T20:45:00","screenName":"Sal 6 LUXE","ticketSaleUrl":"https:\/\/www.odeonkino.no\/api\/v2\/redirect\/show\/Sys99-NO\/81458c3a-f092-421e-bd4e-f3cd0d0805c1","theaterName":"Sandnes Kino","movieVersionId":"BVI20230765"},{"firmName":"Sandnes Kino","showStart":"2024-02-11T20:00:00","screenName":"Sal 6 LUXE","ticketSaleUrl":"https:\/\/www.odeonkino.no\/api\/v2\/redirect\/show\/Sys99-NO\/247042d4-7541-4900-be29-c9b2e0d95292","theaterName":"Sandnes Kino","movieVersionId":"BVI20230765"},{"firmName":"Sandnes Kino","showStart":"2024-02-12T20:00:00","screenName":"Sal 6 LUXE","ticketSaleUrl":"https:\/\/www.odeonkino.no\/api\/v2\/redirect\/show\/Sys99-NO\/12e9b824-049c-46bf-bdca-a1e5aac0468a","theaterName":"Sandnes Kino","movieVersionId":"BVI20230765"},{"firmName":"Sandnes Kino","showStart":"2024-02-13T20:00:00","screenName":"Sal 6 LUXE","ticketSaleUrl":"https:\/\/www.odeonkino.no\/api\/v2\/redirect\/show\/Sys99-NO\/6cf16e72-fba2-4fe4-933d-555c26a50373","theaterName":"Sandnes Kino","movieVersionId":"BVI20230765"}]},{"mainVersionId":"MPL20240053","title":"Sami\u00a0Swoi.\u00a0Poczatek","genres":[],"lengthInMinutes":0,"rating":"12 \u00e5r","poster":null,"sanityImagePosterUrl":"https:\/\/cdn.sanity.io\/images\/j0wdmpyb\/production\/1791b0f0d3927492e72a6290f8d52531beec8a67-765x956.jpg?auto=format","shows":[{"firmName":"Sandnes Kino","showStart":"2024-03-01T20:30:00","screenName":"Sal 4 Sandnes","ticketSaleUrl":"https:\/\/www.odeonkino.no\/api\/v2\/redirect\/show\/Sys99-NO\/5a290d36-24fa-44b0-8089-ac73e3cf0076","theaterName":"Sandnes Kino","movieVersionId":"MPL20240053"}]},{"mainVersionId":"NFD20230381","title":"Sau","genres":["Dokumentar"],"lengthInMinutes":83,"rating":"9 \u00e5r","poster":{"versions":[{"url":"https:\/\/www.filmweb.no\/article1519968.ece\/REPRESENTATIONS\/poster_100x141\/Sau%201080x1920-1.jpg"},{"url":"https:\/\/www.filmweb.no\/article1519968.ece\/REPRESENTATIONS\/poster_200x282\/Sau%201080x1920-1.jpg"},{"url":"https:\/\/www.filmweb.no\/article1519968.ece\/REPRESENTATIONS\/poster_300x424\/Sau%201080x1920-1.jpg"},{"url":"https:\/\/www.filmweb.no\/article1519968.ece\/REPRESENTATIONS\/poster_400x564\/Sau%201080x1920-1.jpg"},{"url":"https:\/\/www.filmweb.no\/article1519968.ece\/REPRESENTATIONS\/poster_600x848\/Sau%201080x1920-1.jpg"}]},"sanityImagePosterUrl":"https:\/\/cdn.sanity.io\/images\/j0wdmpyb\/production\/c3137afb22fb051e2d717c3fc1b17e7955439bbb-1080x1920.jpg?auto=format","shows":[{"firmName":"Sandnes Kino","showStart":"2024-02-08T18:00:00","screenName":"Sal 7 - VIP","ticketSaleUrl":"https:\/\/www.odeonkino.no\/api\/v2\/redirect\/show\/Sys99-NO\/f5794150-f9e1-4a54-ba45-9074c1566158","theaterName":"Sandnes Kino","movieVersionId":"NFD20230381"},{"firmName":"Sandnes Kino","showStart":"2024-02-08T20:15:00","screenName":"Sal 7 - VIP","ticketSaleUrl":"https:\/\/www.odeonkino.no\/api\/v2\/redirect\/show\/Sys99-NO\/5832bcd6-c771-44a3-8009-99def27fcbea","theaterName":"Sandnes Kino","movieVersionId":"NFD20230381"},{"firmName":"Sandnes Kino","showStart":"2024-02-09T18:45:00","screenName":"Sal 7 - VIP","ticketSaleUrl":"https:\/\/www.odeonkino.no\/api\/v2\/redirect\/show\/Sys99-NO\/a59e6a27-a840-44cd-a6ee-740a9f11b983","theaterName":"Sandnes Kino","movieVersionId":"NFD20230381"},{"firmName":"Sandnes Kino","showStart":"2024-02-10T15:45:00","screenName":"Sal 7 - VIP","ticketSaleUrl":"https:\/\/www.odeonkino.no\/api\/v2\/redirect\/show\/Sys99-NO\/f1a73c71-5b14-4c3b-8fb6-b823c6a2d105","theaterName":"Sandnes Kino","movieVersionId":"NFD20230381"}]},{"mainVersionId":"YME20230077","title":"Superkompisene","genres":["Animasjon","Barnefilm","Familiefilm"],"lengthInMinutes":90,"rating":"6 \u00e5r","poster":{"versions":[{"url":"https:\/\/www.filmweb.no\/article1520061.ece\/REPRESENTATIONS\/poster_100x141\/Superkompisene%20TheInseparables_Poster_70x100_Credit_NO.jpg"},{"url":"https:\/\/www.filmweb.no\/article1520061.ece\/REPRESENTATIONS\/poster_200x282\/Superkompisene%20TheInseparables_Poster_70x100_Credit_NO.jpg"},{"url":"https:\/\/www.filmweb.no\/article1520061.ece\/REPRESENTATIONS\/poster_300x424\/Superkompisene%20TheInseparables_Poster_70x100_Credit_NO.jpg"},{"url":"https:\/\/www.filmweb.no\/article1520061.ece\/REPRESENTATIONS\/poster_400x564\/Superkompisene%20TheInseparables_Poster_70x100_Credit_NO.jpg"},{"url":"https:\/\/www.filmweb.no\/article1520061.ece\/REPRESENTATIONS\/poster_600x848\/Superkompisene%20TheInseparables_Poster_70x100_Credit_NO.jpg"}]},"sanityImagePosterUrl":"https:\/\/cdn.sanity.io\/images\/j0wdmpyb\/production\/98f8807f33858a71158b7273ffc1712ed915b8af-1500x2143.webp?auto=format","shows":[{"firmName":"Sandnes Kino","showStart":"2024-02-08T16:20:00","screenName":"Sal 5 Sandnes","ticketSaleUrl":"https:\/\/www.odeonkino.no\/api\/v2\/redirect\/show\/Sys99-NO\/a20355b4-6d09-4fdd-9949-c33ebf98e586","theaterName":"Sandnes Kino","movieVersionId":"YME20240116"},{"firmName":"Sandnes Kino","showStart":"2024-02-09T16:45:00","screenName":"Sal 1 - isense by BATE","ticketSaleUrl":"https:\/\/www.odeonkino.no\/api\/v2\/redirect\/show\/Sys99-NO\/69211894-c267-4c5a-94e8-9b0855b19219","theaterName":"Sandnes Kino","movieVersionId":"YME20240116"},{"firmName":"Sandnes Kino","showStart":"2024-02-10T11:00:00","screenName":"Sal 6 LUXE","ticketSaleUrl":"https:\/\/www.odeonkino.no\/api\/v2\/redirect\/show\/Sys99-NO\/949c4c35-769d-434f-a231-db7cf89ed194","theaterName":"Sandnes Kino","movieVersionId":"YME20240116"},{"firmName":"Sandnes Kino","showStart":"2024-02-10T13:30:00","screenName":"Sal 6 LUXE","ticketSaleUrl":"https:\/\/www.odeonkino.no\/api\/v2\/redirect\/show\/Sys99-NO\/ffb14277-33a6-4461-81c2-de4bc6904307","theaterName":"Sandnes Kino","movieVersionId":"YME20240116"},{"firmName":"Sandnes Kino","showStart":"2024-02-11T15:00:00","screenName":"Sal 5 Sandnes","ticketSaleUrl":"https:\/\/www.odeonkino.no\/api\/v2\/redirect\/show\/Sys99-NO\/cac1873c-1f1f-46b2-97d8-944e1135226d","theaterName":"Sandnes Kino","movieVersionId":"YME20240116"}]},{"mainVersionId":"YME20230105","title":"The Beekeeper","genres":["Action"],"lengthInMinutes":105,"rating":"15 \u00e5r","poster":{"versions":[{"url":"https:\/\/www.filmweb.no\/article1518773.ece\/REPRESENTATIONS\/poster_100x141\/The%20Beekeeper%20TheBeekeeper_Poster_70x100_NO.jpg"},{"url":"https:\/\/www.filmweb.no\/article1518773.ece\/REPRESENTATIONS\/poster_200x282\/The%20Beekeeper%20TheBeekeeper_Poster_70x100_NO.jpg"},{"url":"https:\/\/www.filmweb.no\/article1518773.ece\/REPRESENTATIONS\/poster_300x424\/The%20Beekeeper%20TheBeekeeper_Poster_70x100_NO.jpg"},{"url":"https:\/\/www.filmweb.no\/article1518773.ece\/REPRESENTATIONS\/poster_400x564\/The%20Beekeeper%20TheBeekeeper_Poster_70x100_NO.jpg"},{"url":"https:\/\/www.filmweb.no\/article1518773.ece\/REPRESENTATIONS\/poster_600x848\/The%20Beekeeper%20TheBeekeeper_Poster_70x100_NO.jpg"}]},"sanityImagePosterUrl":"https:\/\/cdn.sanity.io\/images\/j0wdmpyb\/production\/0f8162617910c752a808ad0411ff0b4271858469-1000x1429.webp?auto=format","shows":[{"firmName":"Sandnes Kino","showStart":"2024-02-09T19:00:00","screenName":"Sal 1 - isense by BATE","ticketSaleUrl":"https:\/\/www.odeonkino.no\/api\/v2\/redirect\/show\/Sys99-NO\/eb4a8ef1-e299-45fd-a0e2-e98f72289e57","theaterName":"Sandnes Kino","movieVersionId":"YME20230105"},{"firmName":"Sandnes Kino","showStart":"2024-02-09T21:30:00","screenName":"Sal 1 - isense by BATE","ticketSaleUrl":"https:\/\/www.odeonkino.no\/api\/v2\/redirect\/show\/Sys99-NO\/2d402c2a-d336-44f1-b63f-dd447e385062","theaterName":"Sandnes Kino","movieVersionId":"YME20230105"},{"firmName":"Sandnes Kino","showStart":"2024-02-10T15:45:00","screenName":"Sal 6 LUXE","ticketSaleUrl":"https:\/\/www.odeonkino.no\/api\/v2\/redirect\/show\/Sys99-NO\/a3c2e7ec-e105-4e12-a8d6-17afeda27982","theaterName":"Sandnes Kino","movieVersionId":"YME20230105"},{"firmName":"Sandnes Kino","showStart":"2024-02-10T19:00:00","screenName":"Sal 1 - isense by BATE","ticketSaleUrl":"https:\/\/www.odeonkino.no\/api\/v2\/redirect\/show\/Sys99-NO\/837d03c4-a891-4f6b-9a0b-c09e728d7f83","theaterName":"Sandnes Kino","movieVersionId":"YME20230105"},{"firmName":"Sandnes Kino","showStart":"2024-02-10T21:30:00","screenName":"Sal 1 - isense by BATE","ticketSaleUrl":"https:\/\/www.odeonkino.no\/api\/v2\/redirect\/show\/Sys99-NO\/f82ba2a9-171d-407e-bc6f-2c2f16216ade","theaterName":"Sandnes Kino","movieVersionId":"YME20230105"},{"firmName":"Sandnes Kino","showStart":"2024-02-11T15:00:00","screenName":"Sal 6 LUXE","ticketSaleUrl":"https:\/\/www.odeonkino.no\/api\/v2\/redirect\/show\/Sys99-NO\/4fbc2bf6-9d7b-42de-b9fa-5609ad54a09a","theaterName":"Sandnes Kino","movieVersionId":"YME20230105"},{"firmName":"Sandnes Kino","showStart":"2024-02-11T18:30:00","screenName":"Sal 1 - isense by BATE","ticketSaleUrl":"https:\/\/www.odeonkino.no\/api\/v2\/redirect\/show\/Sys99-NO\/e188132d-e2cc-4137-af3c-20a38e304b9c","theaterName":"Sandnes Kino","movieVersionId":"YME20230105"},{"firmName":"Sandnes Kino","showStart":"2024-02-11T21:00:00","screenName":"Sal 1 - isense by BATE","ticketSaleUrl":"https:\/\/www.odeonkino.no\/api\/v2\/redirect\/show\/Sys99-NO\/2a7bd3cc-6b63-479c-a301-7560e3f3d578","theaterName":"Sandnes Kino","movieVersionId":"YME20230105"},{"firmName":"Sandnes Kino","showStart":"2024-02-12T18:30:00","screenName":"Sal 1 - isense by BATE","ticketSaleUrl":"https:\/\/www.odeonkino.no\/api\/v2\/redirect\/show\/Sys99-NO\/46459f4d-23b1-4208-9831-999e47f5fd3b","theaterName":"Sandnes Kino","movieVersionId":"YME20230105"},{"firmName":"Sandnes Kino","showStart":"2024-02-12T21:00:00","screenName":"Sal 1 - isense by BATE","ticketSaleUrl":"https:\/\/www.odeonkino.no\/api\/v2\/redirect\/show\/Sys99-NO\/e6735ee0-bf8c-493a-aab3-119916535d25","theaterName":"Sandnes Kino","movieVersionId":"YME20230105"},{"firmName":"Sandnes Kino","showStart":"2024-02-13T18:30:00","screenName":"Sal 1 - isense by BATE","ticketSaleUrl":"https:\/\/www.odeonkino.no\/api\/v2\/redirect\/show\/Sys99-NO\/c732a317-8350-4236-b2df-dc42e9e3c8fd","theaterName":"Sandnes Kino","movieVersionId":"YME20230105"},{"firmName":"Sandnes Kino","showStart":"2024-02-13T21:00:00","screenName":"Sal 1 - isense by BATE","ticketSaleUrl":"https:\/\/www.odeonkino.no\/api\/v2\/redirect\/show\/Sys99-NO\/8b06b94c-cb7c-4a1d-b9cd-30fd9201d11a","theaterName":"Sandnes Kino","movieVersionId":"YME20230105"},{"firmName":"Sandnes Kino","showStart":"2024-02-14T21:00:00","screenName":"Sal 3 Sandnes","ticketSaleUrl":"https:\/\/www.odeonkino.no\/api\/v2\/redirect\/show\/Sys99-NO\/7c72560b-edca-49d5-9116-944503a82c04","theaterName":"Sandnes Kino","movieVersionId":"YME20230105"},{"firmName":"Sandnes Kino","showStart":"2024-02-15T21:00:00","screenName":"Sal 3 Sandnes","ticketSaleUrl":"https:\/\/www.odeonkino.no\/api\/v2\/redirect\/show\/Sys99-NO\/a3989b3f-dc10-4c7d-a761-e80688d1c96f","theaterName":"Sandnes Kino","movieVersionId":"YME20230105"}]},{"mainVersionId":"SFN20231697","title":"The Zone of Interest","genres":["Drama"],"lengthInMinutes":105,"rating":"12 \u00e5r","poster":{"versions":[{"url":"https:\/\/www.filmweb.no\/article1518717.ece\/REPRESENTATIONS\/poster_100x141\/The%20Zone%20of%20Interest%20A4_skjerm%20-%20Teaser"},{"url":"https:\/\/www.filmweb.no\/article1518717.ece\/REPRESENTATIONS\/poster_200x282\/The%20Zone%20of%20Interest%20A4_skjerm%20-%20Teaser"},{"url":"https:\/\/www.filmweb.no\/article1518717.ece\/REPRESENTATIONS\/poster_300x424\/The%20Zone%20of%20Interest%20A4_skjerm%20-%20Teaser"},{"url":"https:\/\/www.filmweb.no\/article1518717.ece\/REPRESENTATIONS\/poster_400x564\/The%20Zone%20of%20Interest%20A4_skjerm%20-%20Teaser"},{"url":"https:\/\/www.filmweb.no\/article1518717.ece\/REPRESENTATIONS\/poster_600x848\/The%20Zone%20of%20Interest%20A4_skjerm%20-%20Teaser"}]},"sanityImagePosterUrl":"https:\/\/cdn.sanity.io\/images\/j0wdmpyb\/production\/e5bf1f9f5a41ff606cd0bd10ad87ba9ce2b544d1-1000x1415.webp?auto=format","shows":[{"firmName":"Sandnes Kino","showStart":"2024-02-08T18:30:00","screenName":"Sal 4 Sandnes","ticketSaleUrl":"https:\/\/www.odeonkino.no\/api\/v2\/redirect\/show\/Sys99-NO\/4278fab6-ff1d-479b-983b-0fb114713f1c","theaterName":"Sandnes Kino","movieVersionId":"SFN20231697"},{"firmName":"Sandnes Kino","showStart":"2024-02-10T18:00:00","screenName":"Sal 7 - VIP","ticketSaleUrl":"https:\/\/www.odeonkino.no\/api\/v2\/redirect\/show\/Sys99-NO\/26a60c5f-ce3c-4bcd-9c22-3800db8187a6","theaterName":"Sandnes Kino","movieVersionId":"SFN20231697"}]},{"mainVersionId":"AWE20230452","title":"Vermin","genres":["Action","Gr\u00f8sser","Horror","Skrekkfilm"],"lengthInMinutes":103,"rating":"15 \u00e5r","poster":null,"sanityImagePosterUrl":"https:\/\/cdn.sanity.io\/images\/j0wdmpyb\/production\/3c1be4bbda34bf417778babf23ce6284ff1ace90-1500x2143.webp?auto=format","shows":[{"firmName":"Sandnes Kino","showStart":"2024-02-08T21:00:00","screenName":"Sal 5 Sandnes","ticketSaleUrl":"https:\/\/www.odeonkino.no\/api\/v2\/redirect\/show\/Sys99-NO\/e70d6b69-dc8d-4fc8-951f-050bd076de0d","theaterName":"Sandnes Kino","movieVersionId":"AWE20230452"}]},{"mainVersionId":"SFN20211337","title":"Wonka","genres":["Familiefilm"],"lengthInMinutes":116,"rating":"6 \u00e5r","poster":{"versions":[{"url":"https:\/\/www.filmweb.no\/article1519209.ece\/REPRESENTATIONS\/poster_100x141\/Wonka%20Wonka%20hovedplakat%20A4.jpg"},{"url":"https:\/\/www.filmweb.no\/article1519209.ece\/REPRESENTATIONS\/poster_200x282\/Wonka%20Wonka%20hovedplakat%20A4.jpg"},{"url":"https:\/\/www.filmweb.no\/article1519209.ece\/REPRESENTATIONS\/poster_300x424\/Wonka%20Wonka%20hovedplakat%20A4.jpg"},{"url":"https:\/\/www.filmweb.no\/article1519209.ece\/REPRESENTATIONS\/poster_400x564\/Wonka%20Wonka%20hovedplakat%20A4.jpg"},{"url":"https:\/\/www.filmweb.no\/article1519209.ece\/REPRESENTATIONS\/poster_600x848\/Wonka%20Wonka%20hovedplakat%20A4.jpg"}]},"sanityImagePosterUrl":"https:\/\/cdn.sanity.io\/images\/j0wdmpyb\/production\/64ccaf10250bb0cbbd41b21a4c9767ab0c374760-595x842.jpg?auto=format","shows":[{"firmName":"Sandnes Kino","showStart":"2024-02-09T18:30:00","screenName":"Sal 5 Sandnes","ticketSaleUrl":"https:\/\/www.odeonkino.no\/api\/v2\/redirect\/show\/Sys99-NO\/9b5183e5-560f-4d41-a44f-eb4a4f2578c8","theaterName":"Sandnes Kino","movieVersionId":"SFN20211337"},{"firmName":"Sandnes Kino","showStart":"2024-02-10T15:00:00","screenName":"Sal 5 Sandnes","ticketSaleUrl":"https:\/\/www.odeonkino.no\/api\/v2\/redirect\/show\/Sys99-NO\/bed01d46-7132-40dd-8800-643eae614ad2","theaterName":"Sandnes Kino","movieVersionId":"WAB20230188"},{"firmName":"Sandnes Kino","showStart":"2024-02-10T16:20:00","screenName":"Sal 1 - isense by BATE","ticketSaleUrl":"https:\/\/www.odeonkino.no\/api\/v2\/redirect\/show\/Sys99-NO\/c15f4c73-9a6d-466f-8fae-27225f557ba0","theaterName":"Sandnes Kino","movieVersionId":"SFN20211337"},{"firmName":"Sandnes Kino","showStart":"2024-02-10T18:00:00","screenName":"Sal 5 Sandnes","ticketSaleUrl":"https:\/\/www.odeonkino.no\/api\/v2\/redirect\/show\/Sys99-NO\/9bc6b021-a062-4cf0-9e8e-b08333f9ff49","theaterName":"Sandnes Kino","movieVersionId":"SFN20211337"},{"firmName":"Sandnes Kino","showStart":"2024-02-11T15:20:00","screenName":"Sal 3 Sandnes","ticketSaleUrl":"https:\/\/www.odeonkino.no\/api\/v2\/redirect\/show\/Sys99-NO\/f0b6160c-d420-4be2-8339-7d08352467d0","theaterName":"Sandnes Kino","movieVersionId":"WAB20230189"},{"firmName":"Sandnes Kino","showStart":"2024-02-11T17:30:00","screenName":"Sal 5 Sandnes","ticketSaleUrl":"https:\/\/www.odeonkino.no\/api\/v2\/redirect\/show\/Sys99-NO\/d7868196-fa50-445a-9cc5-59fb373bf5ab","theaterName":"Sandnes Kino","movieVersionId":"SFN20211337"},{"firmName":"Sandnes Kino","showStart":"2024-02-12T17:30:00","screenName":"Sal 5 Sandnes","ticketSaleUrl":"https:\/\/www.odeonkino.no\/api\/v2\/redirect\/show\/Sys99-NO\/1c517b1d-52c1-4615-aa49-b8c0d0e58c80","theaterName":"Sandnes Kino","movieVersionId":"SFN20211337"},{"firmName":"Sandnes Kino","showStart":"2024-02-13T17:30:00","screenName":"Sal 5 Sandnes","ticketSaleUrl":"https:\/\/www.odeonkino.no\/api\/v2\/redirect\/show\/Sys99-NO\/00305cba-75db-4b80-9f45-b87b0a786f49","theaterName":"Sandnes Kino","movieVersionId":"SFN20211337"}]},{"mainVersionId":"BVI20230695","title":"\u00d8nske","genres":["Animasjon","Eventyr","Familiefilm"],"lengthInMinutes":92,"rating":"6 \u00e5r","poster":{"versions":[{"url":"https:\/\/www.filmweb.no\/article1517968.ece\/REPRESENTATIONS\/poster_100x141\/%C3%98nske%20Payoff%20poster"},{"url":"https:\/\/www.filmweb.no\/article1517968.ece\/REPRESENTATIONS\/poster_200x282\/%C3%98nske%20Payoff%20poster"},{"url":"https:\/\/www.filmweb.no\/article1517968.ece\/REPRESENTATIONS\/poster_300x424\/%C3%98nske%20Payoff%20poster"},{"url":"https:\/\/www.filmweb.no\/article1517968.ece\/REPRESENTATIONS\/poster_400x564\/%C3%98nske%20Payoff%20poster"},{"url":"https:\/\/www.filmweb.no\/article1517968.ece\/REPRESENTATIONS\/poster_600x848\/%C3%98nske%20Payoff%20poster"}]},"sanityImagePosterUrl":"https:\/\/cdn.sanity.io\/images\/j0wdmpyb\/production\/2fb9d686b61c9cea3dd85048f44c26d370dfb25b-1000x1429.webp?auto=format","shows":[{"firmName":"Sandnes Kino","showStart":"2024-02-10T13:00:00","screenName":"Sal 4 Sandnes","ticketSaleUrl":"https:\/\/www.odeonkino.no\/api\/v2\/redirect\/show\/Sys99-NO\/8f436567-c5ce-448e-bb1c-deec22997d8c","theaterName":"Sandnes Kino","movieVersionId":"BVI20230695"},{"firmName":"Sandnes Kino","showStart":"2024-02-11T13:10:00","screenName":"Sal 7 - VIP","ticketSaleUrl":"https:\/\/www.odeonkino.no\/api\/v2\/redirect\/show\/Sys99-NO\/5ddc41f8-f68e-4582-894b-acb991a517e7","theaterName":"Sandnes Kino","movieVersionId":"BVI20230695"},{"firmName":"Sandnes Kino","showStart":"2024-02-13T17:00:00","screenName":"Sal 4 Sandnes","ticketSaleUrl":"https:\/\/www.odeonkino.no\/api\/v2\/redirect\/show\/Sys99-NO\/3f0b7781-7283-4a72-b718-d93c72828813","theaterName":"Sandnes Kino","movieVersionId":"BVI20230695"}]}]